{
    "song": {
        "speed": "1.5",
        "stage": "Philly",
        "player1": "Bf",
        "player2": "Pico",
        "gf": "Gf",
        "song": "Pico",
        "bpm": 150,
        "notes": [
            {
                "lengthInSteps": 16,
                "sectionNotes": [],
                "bpm": 0,
                "changeBPM": null,
                "mustHitSection": false
            },
            {
                "lengthInSteps": 16,
                "sectionNotes": [],
                "bpm": 0,
                "changeBPM": null,
                "mustHitSection": false
            },
            {
                "lengthInSteps": 16,
                "sectionNotes": [
                    [
                        3799,
                        2,
                        0,
                        ""
                    ],
                    [
                        4600,
                        0,
                        0,
                        ""
                    ]
                ],
                "bpm": 0,
                "changeBPM": null,
                "mustHitSection": false
            },
            {
                "lengthInSteps": 16,
                "sectionNotes": [
                    [
                        5000,
                        0,
                        0,
                        ""
                    ],
                    [
                        5400,
                        2,
                        0,
                        ""
                    ],
                    [
                        6200,
                        0,
                        0,
                        ""
                    ]
                ],
                "bpm": 0,
                "changeBPM": null,
                "mustHitSection": false
            },
            {
                "lengthInSteps": 16,
                "sectionNotes": [
                    [
                        6999,
                        2,
                        0,
                        ""
                    ],
                    [
                        7799,
                        0,
                        0,
                        ""
                    ]
                ],
                "bpm": 0,
                "changeBPM": null,
                "mustHitSection": false
            },
            {
                "lengthInSteps": 16,
                "sectionNotes": [
                    [
                        8200,
                        0,
                        0,
                        ""
                    ],
                    [
                        8600,
                        2,
                        0,
                        ""
                    ],
                    [
                        9400,
                        0,
                        0,
                        ""
                    ]
                ],
                "bpm": 0,
                "changeBPM": null,
                "mustHitSection": false
            },
            {
                "lengthInSteps": 16,
                "sectionNotes": [
                    [
                        10200,
                        2,
                        0,
                        ""
                    ],
                    [
                        11000,
                        0,
                        0,
                        ""
                    ]
                ],
                "bpm": 0,
                "changeBPM": null,
                "mustHitSection": true
            },
            {
                "lengthInSteps": 16,
                "sectionNotes": [
                    [
                        11400,
                        0,
                        0,
                        ""
                    ],
                    [
                        11800,
                        2,
                        0,
                        ""
                    ],
                    [
                        12600,
                        0,
                        0,
                        ""
                    ]
                ],
                "bpm": 0,
                "changeBPM": null,
                "mustHitSection": true
            },
            {
                "lengthInSteps": 16,
                "sectionNotes": [
                    [
                        13399,
                        2,
                        0,
                        ""
                    ],
                    [
                        14199,
                        0,
                        0,
                        ""
                    ]
                ],
                "bpm": 0,
                "changeBPM": null,
                "mustHitSection": true
            },
            {
                "lengthInSteps": 16,
                "sectionNotes": [
                    [
                        14599,
                        0,
                        0,
                        ""
                    ],
                    [
                        14999,
                        2,
                        0,
                        ""
                    ],
                    [
                        15799,
                        0,
                        0,
                        ""
                    ]
                ],
                "bpm": 0,
                "changeBPM": null,
                "mustHitSection": true
            },
            {
                "lengthInSteps": 16,
                "sectionNotes": [
                    [
                        16199,
                        2,
                        0,
                        ""
                    ],
                    [
                        16800,
                        3,
                        0,
                        ""
                    ],
                    [
                        17200,
                        1,
                        0,
                        ""
                    ]
                ],
                "bpm": 0,
                "changeBPM": null,
                "mustHitSection": false
            },
            {
                "lengthInSteps": 16,
                "sectionNotes": [
                    [
                        17800,
                        3,
                        0,
                        ""
                    ],
                    [
                        18400,
                        2,
                        0,
                        ""
                    ],
                    [
                        18800,
                        1,
                        0,
                        ""
                    ]
                ],
                "bpm": 0,
                "changeBPM": null,
                "mustHitSection": false
            },
            {
                "lengthInSteps": 16,
                "sectionNotes": [
                    [
                        19400,
                        3,
                        0,
                        ""
                    ],
                    [
                        20000,
                        2,
                        0,
                        ""
                    ],
                    [
                        20400,
                        1,
                        0,
                        ""
                    ]
                ],
                "bpm": 0,
                "changeBPM": null,
                "mustHitSection": false
            },
            {
                "lengthInSteps": 16,
                "sectionNotes": [
                    [
                        21000,
                        2,
                        0,
                        ""
                    ],
                    [
                        21600,
                        3,
                        0,
                        ""
                    ],
                    [
                        22000,
                        1,
                        0,
                        ""
                    ]
                ],
                "bpm": 0,
                "changeBPM": null,
                "mustHitSection": false
            },
            {
                "lengthInSteps": 16,
                "sectionNotes": [
                    [
                        22600,
                        2,
                        0,
                        ""
                    ],
                    [
                        23200,
                        3,
                        0,
                        ""
                    ],
                    [
                        23600,
                        1,
                        0,
                        ""
                    ]
                ],
                "bpm": 0,
                "changeBPM": null,
                "mustHitSection": true
            },
            {
                "lengthInSteps": 16,
                "sectionNotes": [
                    [
                        24200,
                        3,
                        0,
                        ""
                    ],
                    [
                        24800,
                        2,
                        0,
                        ""
                    ],
                    [
                        25200,
                        1,
                        0,
                        ""
                    ]
                ],
                "bpm": 0,
                "changeBPM": null,
                "mustHitSection": true
            },
            {
                "lengthInSteps": 16,
                "sectionNotes": [
                    [
                        25799,
                        3,
                        0,
                        ""
                    ],
                    [
                        26399,
                        2,
                        0,
                        ""
                    ],
                    [
                        26799,
                        1,
                        0,
                        ""
                    ]
                ],
                "bpm": 0,
                "changeBPM": null,
                "mustHitSection": true
            },
            {
                "lengthInSteps": 16,
                "sectionNotes": [
                    [
                        27399,
                        2,
                        0,
                        ""
                    ],
                    [
                        27999,
                        3,
                        0,
                        ""
                    ],
                    [
                        28399,
                        1,
                        0,
                        ""
                    ]
                ],
                "bpm": 0,
                "changeBPM": null,
                "mustHitSection": true
            },
            {
                "lengthInSteps": 16,
                "sectionNotes": [
                    [
                        28999,
                        0,
                        0,
                        ""
                    ],
                    [
                        29599,
                        2,
                        0,
                        ""
                    ],
                    [
                        29999,
                        1,
                        0,
                        ""
                    ],
                    [
                        30199,
                        3,
                        0,
                        ""
                    ]
                ],
                "bpm": 0,
                "changeBPM": null,
                "mustHitSection": false
            },
            {
                "lengthInSteps": 16,
                "sectionNotes": [
                    [
                        30400,
                        2,
                        200,
                        ""
                    ],
                    [
                        30800,
                        3,
                        200,
                        ""
                    ],
                    [
                        31199,
                        0,
                        300,
                        ""
                    ],
                    [
                        31599,
                        1,
                        200,
                        ""
                    ]
                ],
                "bpm": 0,
                "changeBPM": null,
                "mustHitSection": false
            },
            {
                "lengthInSteps": 16,
                "sectionNotes": [
                    [
                        32199,
                        3,
                        0,
                        ""
                    ],
                    [
                        32800,
                        3,
                        0,
                        ""
                    ],
                    [
                        33200,
                        2,
                        0,
                        ""
                    ],
                    [
                        33400,
                        3,
                        0,
                        ""
                    ]
                ],
                "bpm": 0,
                "changeBPM": null,
                "mustHitSection": false
            },
            {
                "lengthInSteps": 16,
                "sectionNotes": [
                    [
                        33600,
                        0,
                        200,
                        ""
                    ],
                    [
                        34000,
                        3,
                        200,
                        ""
                    ],
                    [
                        34400,
                        2,
                        300,
                        ""
                    ],
                    [
                        34800,
                        1,
                        300,
                        ""
                    ]
                ],
                "bpm": 0,
                "changeBPM": null,
                "mustHitSection": false
            },
            {
                "lengthInSteps": 16,
                "sectionNotes": [
                    [
                        35400,
                        0,
                        0,
                        ""
                    ],
                    [
                        36000,
                        2,
                        0,
                        ""
                    ],
                    [
                        36400,
                        1,
                        0,
                        ""
                    ],
                    [
                        36600,
                        3,
                        0,
                        ""
                    ]
                ],
                "bpm": 0,
                "changeBPM": null,
                "mustHitSection": true
            },
            {
                "lengthInSteps": 16,
                "sectionNotes": [
                    [
                        36800,
                        2,
                        200,
                        ""
                    ],
                    [
                        37200,
                        3,
                        200,
                        ""
                    ],
                    [
                        37600,
                        0,
                        300,
                        ""
                    ],
                    [
                        38000,
                        1,
                        200,
                        ""
                    ]
                ],
                "bpm": 0,
                "changeBPM": null,
                "mustHitSection": true
            },
            {
                "lengthInSteps": 16,
                "sectionNotes": [
                    [
                        38400,
                        3,
                        0,
                        ""
                    ],
                    [
                        38800,
                        1,
                        0,
                        ""
                    ],
                    [
                        39200,
                        3,
                        0,
                        ""
                    ],
                    [
                        39600,
                        2,
                        0,
                        ""
                    ]
                ],
                "bpm": 0,
                "changeBPM": null,
                "mustHitSection": true
            },
            {
                "lengthInSteps": 16,
                "sectionNotes": [
                    [
                        40000,
                        0,
                        200,
                        ""
                    ],
                    [
                        40400,
                        3,
                        200,
                        ""
                    ],
                    [
                        40800,
                        2,
                        300,
                        ""
                    ],
                    [
                        41200,
                        1,
                        300,
                        ""
                    ]
                ],
                "bpm": 0,
                "changeBPM": null,
                "mustHitSection": true
            },
            {
                "lengthInSteps": 16,
                "sectionNotes": [
                    [
                        41800,
                        2,
                        200,
                        ""
                    ],
                    [
                        42400,
                        3,
                        0,
                        ""
                    ],
                    [
                        42800,
                        1,
                        0,
                        ""
                    ]
                ],
                "bpm": 0,
                "changeBPM": null,
                "mustHitSection": false
            },
            {
                "lengthInSteps": 16,
                "sectionNotes": [
                    [
                        43400,
                        2,
                        200,
                        ""
                    ],
                    [
                        44000,
                        3,
                        0,
                        ""
                    ],
                    [
                        44400,
                        1,
                        0,
                        ""
                    ]
                ],
                "bpm": 0,
                "changeBPM": null,
                "mustHitSection": false
            },
            {
                "lengthInSteps": 16,
                "sectionNotes": [
                    [
                        45000,
                        3,
                        200,
                        ""
                    ],
                    [
                        45600,
                        2,
                        0,
                        ""
                    ],
                    [
                        46000,
                        1,
                        0,
                        ""
                    ]
                ],
                "bpm": 0,
                "changeBPM": null,
                "mustHitSection": false
            },
            {
                "lengthInSteps": 16,
                "sectionNotes": [
                    [
                        46600,
                        2,
                        200,
                        ""
                    ],
                    [
                        47200,
                        3,
                        0,
                        ""
                    ],
                    [
                        47600,
                        1,
                        0,
                        ""
                    ]
                ],
                "bpm": 0,
                "changeBPM": null,
                "mustHitSection": false
            },
            {
                "lengthInSteps": 16,
                "sectionNotes": [
                    [
                        48200,
                        2,
                        200,
                        ""
                    ],
                    [
                        48800,
                        3,
                        0,
                        ""
                    ],
                    [
                        49200,
                        1,
                        0,
                        ""
                    ]
                ],
                "bpm": 0,
                "changeBPM": null,
                "mustHitSection": true
            },
            {
                "lengthInSteps": 16,
                "sectionNotes": [
                    [
                        49800,
                        2,
                        200,
                        ""
                    ],
                    [
                        50400,
                        3,
                        0,
                        ""
                    ],
                    [
                        50800,
                        1,
                        0,
                        ""
                    ]
                ],
                "bpm": 0,
                "changeBPM": null,
                "mustHitSection": true
            },
            {
                "lengthInSteps": 16,
                "sectionNotes": [
                    [
                        51400,
                        3,
                        200,
                        ""
                    ],
                    [
                        51999,
                        2,
                        0,
                        ""
                    ],
                    [
                        52399,
                        1,
                        0,
                        ""
                    ]
                ],
                "bpm": 0,
                "changeBPM": null,
                "mustHitSection": true
            },
            {
                "lengthInSteps": 16,
                "sectionNotes": [
                    [
                        53000,
                        2,
                        200,
                        ""
                    ],
                    [
                        53599,
                        3,
                        0,
                        ""
                    ],
                    [
                        53999,
                        1,
                        0,
                        ""
                    ]
                ],
                "bpm": 0,
                "changeBPM": null,
                "mustHitSection": true
            },
            {
                "lengthInSteps": 16,
                "sectionNotes": [
                    [
                        54399,
                        6,
                        200,
                        ""
                    ],
                    [
                        54599,
                        2,
                        0,
                        ""
                    ],
                    [
                        54999,
                        7,
                        0,
                        ""
                    ],
                    [
                        55199,
                        3,
                        0,
                        ""
                    ],
                    [
                        55199,
                        5,
                        0,
                        ""
                    ],
                    [
                        55599,
                        1,
                        0,
                        ""
                    ],
                    [
                        55599,
                        7,
                        0,
                        ""
                    ]
                ],
                "bpm": 0,
                "changeBPM": null,
                "mustHitSection": false
            },
            {
                "lengthInSteps": 16,
                "sectionNotes": [
                    [
                        55999,
                        0,
                        0,
                        ""
                    ],
                    [
                        56199,
                        4,
                        0,
                        ""
                    ],
                    [
                        56499,
                        0,
                        0,
                        ""
                    ],
                    [
                        56799,
                        7,
                        0,
                        ""
                    ],
                    [
                        56799,
                        1,
                        200,
                        ""
                    ],
                    [
                        57199,
                        6,
                        0,
                        ""
                    ]
                ],
                "bpm": 0,
                "changeBPM": null,
                "mustHitSection": true
            },
            {
                "lengthInSteps": 16,
                "sectionNotes": [
                    [
                        57599,
                        6,
                        200,
                        ""
                    ],
                    [
                        57799,
                        3,
                        0,
                        ""
                    ],
                    [
                        58399,
                        2,
                        0,
                        ""
                    ],
                    [
                        58399,
                        5,
                        0,
                        ""
                    ],
                    [
                        58799,
                        1,
                        0,
                        ""
                    ],
                    [
                        58799,
                        7,
                        0,
                        ""
                    ]
                ],
                "bpm": 0,
                "changeBPM": null,
                "mustHitSection": false
            },
            {
                "lengthInSteps": 16,
                "sectionNotes": [
                    [
                        59199,
                        4,
                        0,
                        ""
                    ],
                    [
                        59399,
                        0,
                        0,
                        ""
                    ],
                    [
                        59699,
                        4,
                        0,
                        ""
                    ],
                    [
                        59999,
                        3,
                        0,
                        ""
                    ],
                    [
                        60099,
                        6,
                        0,
                        ""
                    ],
                    [
                        60399,
                        2,
                        0,
                        ""
                    ],
                    [
                        60499,
                        4,
                        0,
                        ""
                    ]
                ],
                "bpm": 0,
                "changeBPM": null,
                "mustHitSection": false
            },
            {
                "lengthInSteps": 16,
                "sectionNotes": [
                    [
                        61000,
                        2,
                        200,
                        ""
                    ],
                    [
                        61599,
                        3,
                        0,
                        ""
                    ],
                    [
                        61999,
                        1,
                        0,
                        ""
                    ]
                ],
                "bpm": 0,
                "changeBPM": null,
                "mustHitSection": true
            },
            {
                "lengthInSteps": 16,
                "sectionNotes": [
                    [
                        62600,
                        0,
                        200,
                        ""
                    ],
                    [
                        63199,
                        3,
                        0,
                        ""
                    ],
                    [
                        63599,
                        2,
                        0,
                        ""
                    ]
                ],
                "bpm": 0,
                "changeBPM": null,
                "mustHitSection": true
            },
            {
                "lengthInSteps": 16,
                "sectionNotes": [
                    [
                        64200,
                        3,
                        200,
                        ""
                    ],
                    [
                        64799,
                        2,
                        0,
                        ""
                    ],
                    [
                        65199,
                        1,
                        0,
                        ""
                    ]
                ],
                "bpm": 0,
                "changeBPM": null,
                "mustHitSection": true
            },
            {
                "lengthInSteps": 16,
                "sectionNotes": [
                    [
                        65800,
                        0,
                        200,
                        ""
                    ],
                    [
                        66400,
                        3,
                        0,
                        ""
                    ],
                    [
                        66800,
                        2,
                        0,
                        ""
                    ]
                ],
                "bpm": 0,
                "changeBPM": null,
                "mustHitSection": true
            },
            {
                "lengthInSteps": 16,
                "sectionNotes": [
                    [
                        67400,
                        0,
                        0,
                        ""
                    ],
                    [
                        68000,
                        2,
                        0,
                        ""
                    ],
                    [
                        68400,
                        1,
                        0,
                        ""
                    ],
                    [
                        68600,
                        3,
                        0,
                        ""
                    ]
                ],
                "bpm": 0,
                "changeBPM": null,
                "mustHitSection": false
            },
            {
                "lengthInSteps": 16,
                "sectionNotes": [
                    [
                        68800,
                        2,
                        200,
                        ""
                    ],
                    [
                        69200,
                        3,
                        200,
                        ""
                    ],
                    [
                        69600,
                        0,
                        300,
                        ""
                    ],
                    [
                        70000,
                        1,
                        200,
                        ""
                    ]
                ],
                "bpm": 0,
                "changeBPM": null,
                "mustHitSection": false
            },
            {
                "lengthInSteps": 16,
                "sectionNotes": [
                    [
                        70600,
                        3,
                        200,
                        ""
                    ],
                    [
                        71200,
                        3,
                        0,
                        ""
                    ],
                    [
                        71600,
                        2,
                        0,
                        ""
                    ],
                    [
                        71800,
                        3,
                        0,
                        ""
                    ]
                ],
                "bpm": 0,
                "changeBPM": null,
                "mustHitSection": false
            },
            {
                "lengthInSteps": 16,
                "sectionNotes": [
                    [
                        72000,
                        0,
                        200,
                        ""
                    ],
                    [
                        72400,
                        3,
                        200,
                        ""
                    ],
                    [
                        72800,
                        2,
                        300,
                        ""
                    ],
                    [
                        73200,
                        1,
                        300,
                        ""
                    ]
                ],
                "bpm": 0,
                "changeBPM": null,
                "mustHitSection": false
            },
            {
                "lengthInSteps": 16,
                "sectionNotes": [
                    [
                        73800,
                        0,
                        200,
                        ""
                    ],
                    [
                        74400,
                        2,
                        0,
                        ""
                    ],
                    [
                        74800,
                        1,
                        0,
                        ""
                    ],
                    [
                        75000,
                        3,
                        0,
                        ""
                    ]
                ],
                "bpm": 0,
                "changeBPM": null,
                "mustHitSection": true
            },
            {
                "lengthInSteps": 16,
                "sectionNotes": [
                    [
                        75200,
                        2,
                        200,
                        ""
                    ],
                    [
                        75600,
                        3,
                        200,
                        ""
                    ],
                    [
                        76000,
                        0,
                        300,
                        ""
                    ],
                    [
                        76400,
                        1,
                        200,
                        ""
                    ]
                ],
                "bpm": 0,
                "changeBPM": null,
                "mustHitSection": true
            },
            {
                "lengthInSteps": 16,
                "sectionNotes": [
                    [
                        76800,
                        3,
                        0,
                        ""
                    ],
                    [
                        77200,
                        1,
                        0,
                        ""
                    ],
                    [
                        77600,
                        3,
                        0,
                        ""
                    ],
                    [
                        78000,
                        2,
                        0,
                        ""
                    ]
                ],
                "bpm": 0,
                "changeBPM": null,
                "mustHitSection": true
            },
            {
                "lengthInSteps": 16,
                "sectionNotes": [
                    [
                        78400,
                        0,
                        200,
                        ""
                    ],
                    [
                        78800,
                        3,
                        200,
                        ""
                    ],
                    [
                        79200,
                        2,
                        300,
                        ""
                    ],
                    [
                        79600,
                        1,
                        300,
                        ""
                    ]
                ],
                "bpm": 0,
                "changeBPM": null,
                "mustHitSection": true
            }
        ]
    }
}