{
	"song": {
		"speed": 2.6,
		"stage": "PhillyErect",
		"player1": "Bf",
		"player2": "Pico",
		"notes": [
			{
				"lengthInSteps": 16,
				"sectionNotes": [],
				"bpm": 0,
				"changeBPM": null,
				"mustHitSection": false
			},
			{
				"lengthInSteps": 16,
				"sectionNotes": [],
				"bpm": 0,
				"changeBPM": null,
				"mustHitSection": false
			},
			{
				"lengthInSteps": 16,
				"sectionNotes": [],
				"bpm": 0,
				"changeBPM": null,
				"mustHitSection": true
			},
			{
				"lengthInSteps": 16,
				"sectionNotes": [],
				"bpm": 0,
				"changeBPM": null,
				"mustHitSection": true
			},
			{
				"lengthInSteps": 16,
				"sectionNotes": [],
				"bpm": 0,
				"changeBPM": null,
				"mustHitSection": false
			},
			{
				"lengthInSteps": 16,
				"sectionNotes": [],
				"bpm": 0,
				"changeBPM": null,
				"mustHitSection": false
			},
			{
				"lengthInSteps": 16,
				"sectionNotes": [],
				"bpm": 0,
				"changeBPM": null,
				"mustHitSection": true
			},
			{
				"lengthInSteps": 16,
				"sectionNotes": [],
				"bpm": 0,
				"changeBPM": null,
				"mustHitSection": true
			},
			{
				"lengthInSteps": 16,
				"sectionNotes": [
					[
						12352,
						3,
						0,
						0
					],
					[
						12176,
						1,
						0,
						0
					],
					[
						12000,
						0,
						0,
						0
					],
					[
						11823,
						0,
						0,
						0
					],
					[
						11647,
						3,
						0,
						0
					],
					[
						11470,
						1,
						0,
						0
					]
				],
				"bpm": 0,
				"changeBPM": null,
				"mustHitSection": false
			},
			{
				"lengthInSteps": 16,
				"sectionNotes": [
					[
						12882,
						0,
						0,
						0
					],
					[
						12705,
						2,
						0,
						0
					],
					[
						13058,
						2,
						0,
						0
					],
					[
						13235,
						3,
						0,
						0
					],
					[
						13323,
						0,
						0,
						0
					],
					[
						13411,
						3,
						0,
						0
					],
					[
						13588,
						3,
						0,
						0
					],
					[
						13764,
						1,
						0,
						0
					]
				],
				"bpm": 0,
				"changeBPM": null,
				"mustHitSection": false
			},
			{
				"lengthInSteps": 16,
				"sectionNotes": [
					[
						14294,
						1,
						0,
						0
					],
					[
						14470,
						3,
						0,
						0
					],
					[
						14647,
						0,
						0,
						0
					],
					[
						14823,
						0,
						0,
						0
					],
					[
						15000,
						1,
						0,
						0
					],
					[
						15176,
						3,
						0,
						0
					],
					[
						15352,
						2,
						0,
						0
					]
				],
				"bpm": 0,
				"changeBPM": null,
				"mustHitSection": false
			},
			{
				"lengthInSteps": 16,
				"sectionNotes": [
					[
						15529,
						3,
						0,
						0
					],
					[
						15705,
						1,
						0,
						0
					],
					[
						15882,
						3,
						0,
						0
					],
					[
						16058,
						2,
						0,
						0
					],
					[
						16235,
						1,
						0,
						0
					],
					[
						16411,
						3,
						0,
						0
					],
					[
						16588,
						1,
						0,
						0
					]
				],
				"bpm": 0,
				"changeBPM": null,
				"mustHitSection": false
			},
			{
				"lengthInSteps": 16,
				"sectionNotes": [
					[
						16941.1764705882,
						1,
						0,
						""
					],
					[
						17029.4117647059,
						0,
						0,
						""
					],
					[
						17117.6470588235,
						1,
						0,
						""
					],
					[
						17294.1176470588,
						3,
						0,
						""
					],
					[
						17382.3529411765,
						2,
						0,
						""
					],
					[
						17470.5882352941,
						0,
						0,
						""
					],
					[
						17647.0588235294,
						0,
						0,
						""
					],
					[
						17735.2941176471,
						1,
						0,
						""
					],
					[
						17823.5294117647,
						3,
						0,
						""
					],
					[
						18000,
						2,
						0,
						""
					],
					[
						18176.4705882353,
						3,
						0,
						""
					],
					[
						18264.7058823529,
						2,
						0,
						""
					]
				],
				"bpm": 0,
				"changeBPM": null,
				"mustHitSection": true
			},
			{
				"lengthInSteps": 16,
				"sectionNotes": [
					[
						18352.9411764706,
						0,
						0,
						""
					],
					[
						18441.1764705882,
						2,
						0,
						""
					],
					[
						18529.4117647059,
						1,
						0,
						""
					],
					[
						18705.8823529412,
						0,
						0,
						""
					],
					[
						18794.1176470588,
						2,
						0,
						""
					],
					[
						18882.3529411764,
						3,
						0,
						""
					],
					[
						18970.5882352941,
						1,
						0,
						""
					],
					[
						19058.8235294117,
						3,
						0,
						""
					],
					[
						19235.2941176471,
						0,
						0,
						""
					],
					[
						19411.7647058823,
						2,
						0,
						""
					],
					[
						19588.2352941176,
						2,
						0,
						""
					]
				],
				"bpm": 0,
				"changeBPM": null,
				"mustHitSection": true
			},
			{
				"lengthInSteps": 16,
				"sectionNotes": [
					[
						21000,
						2,
						88.2352941176468,
						""
					],
					[
						19764.7058823529,
						1,
						0,
						""
					],
					[
						19852.9411764706,
						0,
						0,
						""
					],
					[
						19941.1764705882,
						1,
						0,
						""
					],
					[
						20029.4117647059,
						3,
						0,
						""
					],
					[
						20117.6470588235,
						1,
						0,
						""
					],
					[
						20205.8823529412,
						0,
						0,
						""
					],
					[
						20294.1176470588,
						1,
						0,
						""
					],
					[
						20470.5882352941,
						3,
						0,
						""
					],
					[
						20558.8235294118,
						2,
						0,
						""
					],
					[
						20647.0588235294,
						0,
						0,
						""
					],
					[
						20735.2941176471,
						2,
						0,
						""
					],
					[
						20823.5294117647,
						1,
						0,
						""
					],
					[
						20911.7647058824,
						3,
						0,
						""
					]
				],
				"bpm": 0,
				"changeBPM": null,
				"mustHitSection": true
			},
			{
				"lengthInSteps": 16,
				"sectionNotes": [
					[
						21176.4705882353,
						0,
						0,
						""
					],
					[
						21264.7058823529,
						1,
						0,
						""
					],
					[
						21352.9411764706,
						2,
						0,
						""
					],
					[
						21441.1764705882,
						3,
						0,
						""
					],
					[
						21529.4117647059,
						0,
						0,
						""
					],
					[
						21617.6470588235,
						1,
						0,
						""
					],
					[
						21705.8823529412,
						2,
						0,
						""
					],
					[
						21794.1176470588,
						3,
						0,
						""
					],
					[
						21882.3529411764,
						0,
						0,
						""
					],
					[
						21970.5882352941,
						1,
						0,
						""
					],
					[
						22058.8235294117,
						3,
						0,
						""
					],
					[
						22147.0588235294,
						1,
						0,
						""
					],
					[
						22235.294117647,
						0,
						0,
						""
					],
					[
						22323.5294117647,
						1,
						0,
						""
					],
					[
						22411.7647058823,
						3,
						0,
						""
					],
					[
						22500,
						2,
						0,
						""
					]
				],
				"bpm": 0,
				"changeBPM": null,
				"mustHitSection": true
			},
			{
				"lengthInSteps": 16,
				"sectionNotes": [
					[
						22588,
						5,
						264,
						0
					],
					[
						22764,
						2,
						0,
						0
					],
					[
						22941,
						3,
						0,
						0
					],
					[
						23117,
						3,
						0,
						0
					],
					[
						23294,
						2,
						0,
						0
					],
					[
						23470,
						0,
						0,
						0
					],
					[
						23823,
						1,
						0,
						0
					]
				],
				"bpm": 0,
				"changeBPM": null,
				"mustHitSection": false
			},
			{
				"lengthInSteps": 16,
				"sectionNotes": [
					[
						24000,
						3,
						0,
						0
					],
					[
						24176,
						1,
						0,
						0
					],
					[
						24352,
						0,
						0,
						0
					],
					[
						24529,
						1,
						0,
						0
					],
					[
						24705,
						2,
						0,
						0
					],
					[
						24882,
						3,
						0,
						0
					],
					[
						25058,
						0,
						0,
						0
					],
					[
						25235,
						1,
						0,
						0
					]
				],
				"bpm": 0,
				"changeBPM": null,
				"mustHitSection": false
			},
			{
				"lengthInSteps": 16,
				"sectionNotes": [
					[
						25588,
						2,
						0,
						0
					],
					[
						25764,
						3,
						0,
						0
					],
					[
						25941,
						3,
						0,
						0
					],
					[
						26117,
						1,
						0,
						0
					],
					[
						26294,
						0,
						0,
						0
					],
					[
						26647,
						2,
						0,
						0
					]
				],
				"bpm": 0,
				"changeBPM": null,
				"mustHitSection": false
			},
			{
				"lengthInSteps": 16,
				"sectionNotes": [
					[
						26823,
						3,
						0,
						0
					],
					[
						27000,
						0,
						0,
						0
					],
					[
						27176,
						1,
						0,
						0
					],
					[
						27352,
						1,
						0,
						0
					],
					[
						27529,
						3,
						0,
						0
					],
					[
						27705,
						2,
						0,
						0
					],
					[
						27882,
						1,
						0,
						0
					],
					[
						28058,
						1,
						0,
						0
					]
				],
				"bpm": 0,
				"changeBPM": null,
				"mustHitSection": false
			},
			{
				"lengthInSteps": 16,
				"sectionNotes": [
					[
						29294.1176470588,
						1,
						88.2352941176468,
						""
					],
					[
						28235.2941176471,
						2,
						0,
						""
					],
					[
						28323.5294117647,
						3,
						0,
						""
					],
					[
						28411.7647058823,
						0,
						0,
						""
					],
					[
						28500,
						1,
						0,
						""
					],
					[
						28588.2352941176,
						3,
						0,
						""
					],
					[
						28676.4705882353,
						1,
						0,
						""
					],
					[
						28764.7058823529,
						0,
						0,
						""
					],
					[
						28852.9411764706,
						2,
						0,
						""
					],
					[
						28941.1764705882,
						0,
						0,
						""
					],
					[
						29029.4117647059,
						1,
						0,
						""
					],
					[
						29117.6470588235,
						3,
						0,
						""
					],
					[
						29205.8823529412,
						2,
						0,
						""
					],
					[
						29470.5882352941,
						3,
						0,
						""
					],
					[
						29558.8235294117,
						0,
						0,
						""
					]
				],
				"bpm": 0,
				"changeBPM": null,
				"mustHitSection": true
			},
			{
				"lengthInSteps": 16,
				"sectionNotes": [
					[
						29647.0588235294,
						2,
						0,
						""
					],
					[
						29735.2941176471,
						3,
						0,
						""
					],
					[
						29823.5294117647,
						0,
						0,
						""
					],
					[
						29911.7647058824,
						3,
						0,
						""
					],
					[
						30000,
						1,
						0,
						""
					],
					[
						30088.2352941176,
						0,
						0,
						""
					],
					[
						30176.4705882353,
						1,
						0,
						""
					],
					[
						30264.7058823529,
						0,
						0,
						""
					],
					[
						30352.9411764706,
						3,
						0,
						""
					],
					[
						30529.4117647059,
						2,
						0,
						""
					],
					[
						30617.6470588235,
						1,
						0,
						""
					],
					[
						30705.8823529412,
						0,
						0,
						""
					],
					[
						30794.1176470588,
						3,
						0,
						""
					],
					[
						30882.3529411765,
						2,
						0,
						""
					]
				],
				"bpm": 0,
				"changeBPM": null,
				"mustHitSection": true
			},
			{
				"lengthInSteps": 16,
				"sectionNotes": [
					[
						31941.1764705882,
						2,
						88.2352941176468,
						""
					],
					[
						31764.7058823529,
						3,
						88.2352941176468,
						""
					],
					[
						31588.2352941176,
						1,
						88.2352941176468,
						""
					],
					[
						31235.2941176471,
						2,
						88.2352941176468,
						""
					],
					[
						31058.8235294118,
						0,
						0,
						""
					],
					[
						31147.0588235294,
						3,
						0,
						""
					],
					[
						31411.7647058824,
						0,
						0,
						""
					],
					[
						31500,
						3,
						0,
						""
					],
					[
						32117.6470588235,
						0,
						0,
						""
					],
					[
						32205.8823529412,
						1,
						0,
						""
					],
					[
						32294.1176470588,
						3,
						0,
						""
					],
					[
						32382.3529411764,
						1,
						0,
						""
					]
				],
				"bpm": 0,
				"changeBPM": null,
				"mustHitSection": true
			},
			{
				"lengthInSteps": 16,
				"sectionNotes": [
					[
						32470.5882352941,
						0,
						0,
						""
					],
					[
						32558.8235294118,
						3,
						0,
						""
					],
					[
						32647.0588235294,
						2,
						0,
						""
					],
					[
						32735.2941176471,
						3,
						0,
						""
					],
					[
						32823.5294117647,
						1,
						0,
						""
					],
					[
						32911.7647058823,
						0,
						0,
						""
					],
					[
						33000,
						1,
						0,
						""
					],
					[
						33088.2352941176,
						3,
						0,
						""
					],
					[
						33176.4705882353,
						0,
						0,
						""
					],
					[
						33352.9411764706,
						2,
						0,
						""
					],
					[
						33441.1764705882,
						1,
						0,
						""
					],
					[
						33529.4117647059,
						3,
						0,
						""
					],
					[
						33617.6470588235,
						0,
						0,
						""
					],
					[
						33705.8823529411,
						1,
						0,
						""
					]
				],
				"bpm": 0,
				"changeBPM": null,
				"mustHitSection": true
			},
			{
				"lengthInSteps": 16,
				"sectionNotes": [
					[
						34058,
						0,
						0,
						0
					],
					[
						34235,
						2,
						0,
						0
					],
					[
						34588,
						3,
						0,
						0
					],
					[
						34764,
						3,
						0,
						0
					],
					[
						34941,
						1,
						176,
						0
					]
				],
				"bpm": 0,
				"changeBPM": null,
				"mustHitSection": false
			},
			{
				"lengthInSteps": 16,
				"sectionNotes": [
					[
						35294,
						2,
						0,
						0
					],
					[
						35647,
						3,
						0,
						0
					],
					[
						36000,
						2,
						0,
						0
					],
					[
						36352,
						0,
						0,
						0
					],
					[
						36529,
						3,
						0,
						0
					]
				],
				"bpm": 0,
				"changeBPM": null,
				"mustHitSection": false
			},
			{
				"lengthInSteps": 16,
				"sectionNotes": [
					[
						36882,
						0,
						0,
						0
					],
					[
						37058,
						2,
						0,
						0
					],
					[
						37411,
						3,
						0,
						0
					],
					[
						37588,
						3,
						0,
						0
					],
					[
						37764,
						1,
						176,
						0
					]
				],
				"bpm": 0,
				"changeBPM": null,
				"mustHitSection": false
			},
			{
				"lengthInSteps": 16,
				"sectionNotes": [
					[
						38117,
						0,
						176,
						0
					],
					[
						38470,
						1,
						0,
						0
					],
					[
						38823,
						3,
						0,
						0
					],
					[
						38911,
						3,
						0,
						0
					],
					[
						39000,
						1,
						0,
						0
					],
					[
						39176,
						2,
						0,
						0
					],
					[
						39352,
						3,
						0,
						0
					]
				],
				"bpm": 0,
				"changeBPM": null,
				"mustHitSection": false
			},
			{
				"lengthInSteps": 16,
				"sectionNotes": [
					[
						40588.2352941176,
						2,
						176.470588235294,
						""
					],
					[
						39529.4117647059,
						3,
						0,
						""
					],
					[
						39617.6470588235,
						1,
						0,
						""
					],
					[
						39705.8823529412,
						3,
						0,
						""
					],
					[
						39882.3529411764,
						1,
						0,
						""
					],
					[
						40058.8235294118,
						0,
						0,
						""
					],
					[
						40235.294117647,
						3,
						0,
						""
					],
					[
						40323.5294117647,
						1,
						0,
						""
					],
					[
						40411.7647058823,
						3,
						0,
						""
					],
					[
						40500,
						1,
						0,
						""
					]
				],
				"bpm": 0,
				"changeBPM": null,
				"mustHitSection": true
			},
			{
				"lengthInSteps": 16,
				"sectionNotes": [
					[
						42176.4705882353,
						3,
						88.2352941176505,
						""
					],
					[
						42000,
						1,
						88.2352941176505,
						""
					],
					[
						41823.5294117647,
						0,
						88.2352941176505,
						""
					],
					[
						41647.0588235294,
						2,
						88.2352941176505,
						""
					],
					[
						41470.5882352941,
						1,
						88.2352941176505,
						""
					],
					[
						41294.1176470588,
						3,
						88.2352941176505,
						""
					],
					[
						41117.6470588235,
						2,
						88.2352941176505,
						""
					],
					[
						40941.1764705882,
						0,
						88.2352941176505,
						""
					]
				],
				"bpm": 0,
				"changeBPM": null,
				"mustHitSection": true
			},
			{
				"lengthInSteps": 16,
				"sectionNotes": [
					[
						43411.7647058823,
						1,
						88.2352941176505,
						""
					],
					[
						42529.4117647059,
						0,
						0,
						""
					],
					[
						42705.8823529411,
						2,
						0,
						""
					],
					[
						43058.8235294117,
						3,
						0,
						""
					],
					[
						43235.294117647,
						3,
						0,
						""
					]
				],
				"bpm": 0,
				"changeBPM": null,
				"mustHitSection": true
			},
			{
				"lengthInSteps": 16,
				"sectionNotes": [
					[
						43764.7058823529,
						0,
						0,
						""
					],
					[
						43852.9411764706,
						2,
						0,
						""
					],
					[
						43941.1764705882,
						3,
						0,
						""
					],
					[
						44029.4117647059,
						2,
						0,
						""
					],
					[
						44117.6470588235,
						0,
						0,
						""
					],
					[
						44205.8823529412,
						2,
						0,
						""
					],
					[
						44294.1176470588,
						3,
						0,
						""
					],
					[
						44382.3529411765,
						2,
						0,
						""
					],
					[
						44470.5882352941,
						0,
						0,
						""
					],
					[
						44558.8235294118,
						3,
						0,
						""
					],
					[
						44647.0588235294,
						1,
						0,
						""
					],
					[
						44823.5294117647,
						2,
						0,
						""
					],
					[
						45000,
						3,
						0,
						""
					],
					[
						45044.1176470588,
						2,
						0,
						""
					],
					[
						45088.2352941176,
						1,
						0,
						""
					],
					[
						45132.3529411765,
						0,
						0,
						""
					]
				],
				"bpm": 0,
				"changeBPM": null,
				"mustHitSection": true
			},
			{
				"lengthInSteps": 16,
				"sectionNotes": [
					[
						45176,
						0,
						0,
						0
					],
					[
						45264,
						1,
						0,
						0
					],
					[
						45352,
						0,
						0,
						0
					],
					[
						45441,
						1,
						0,
						0
					],
					[
						45529,
						0,
						0,
						0
					],
					[
						45617,
						3,
						0,
						0
					],
					[
						45705,
						0,
						0,
						0
					],
					[
						45794,
						3,
						0,
						0
					],
					[
						45882,
						1,
						0,
						0
					],
					[
						45970,
						0,
						0,
						0
					],
					[
						46058,
						1,
						0,
						0
					],
					[
						46147,
						3,
						0,
						0
					],
					[
						46235,
						1,
						0,
						0
					],
					[
						46323,
						3,
						0,
						0
					],
					[
						46411,
						1,
						0,
						0
					],
					[
						46500,
						3,
						0,
						0
					]
				],
				"bpm": 0,
				"changeBPM": null,
				"mustHitSection": false
			},
			{
				"lengthInSteps": 16,
				"sectionNotes": [
					[
						46588,
						2,
						0,
						0
					],
					[
						46676,
						3,
						0,
						0
					],
					[
						46764,
						2,
						0,
						0
					],
					[
						46852,
						0,
						0,
						0
					],
					[
						46941,
						3,
						0,
						0
					],
					[
						46985,
						2,
						0,
						0
					],
					[
						47029,
						1,
						0,
						0
					],
					[
						47073,
						0,
						0,
						0
					],
					[
						47117,
						2,
						0,
						0
					],
					[
						47294,
						1,
						0,
						0
					],
					[
						47470,
						0,
						0,
						0
					],
					[
						47558,
						1,
						0,
						0
					],
					[
						47647,
						0,
						0,
						0
					],
					[
						47823,
						1,
						0,
						0
					]
				],
				"bpm": 0,
				"changeBPM": null,
				"mustHitSection": false
			},
			{
				"lengthInSteps": 16,
				"sectionNotes": [
					[
						48000,
						3,
						0,
						0
					],
					[
						48088,
						0,
						0,
						0
					],
					[
						48176,
						3,
						0,
						0
					],
					[
						48264,
						0,
						0,
						0
					],
					[
						48352,
						3,
						0,
						0
					],
					[
						48441,
						3,
						0,
						0
					],
					[
						48529,
						2,
						0,
						0
					],
					[
						48617,
						0,
						0,
						0
					],
					[
						48705,
						2,
						0,
						0
					],
					[
						48794,
						2,
						0,
						0
					],
					[
						48882,
						0,
						0,
						0
					],
					[
						48970,
						1,
						0,
						0
					],
					[
						49058,
						0,
						0,
						0
					],
					[
						49147,
						3,
						0,
						0
					],
					[
						49235,
						0,
						0,
						0
					],
					[
						49323,
						1,
						0,
						0
					]
				],
				"bpm": 0,
				"changeBPM": null,
				"mustHitSection": false
			},
			{
				"lengthInSteps": 16,
				"sectionNotes": [
					[
						49411,
						0,
						0,
						0
					],
					[
						49500,
						2,
						0,
						0
					],
					[
						49588,
						0,
						0,
						0
					],
					[
						49676,
						1,
						0,
						0
					],
					[
						49764,
						3,
						0,
						0
					],
					[
						49808,
						0,
						0,
						0
					],
					[
						49852,
						1,
						0,
						0
					],
					[
						49897,
						2,
						0,
						0
					],
					[
						49941,
						3,
						0,
						0
					],
					[
						50117,
						2,
						0,
						0
					],
					[
						50294,
						0,
						0,
						0
					],
					[
						50382,
						3,
						0,
						0
					],
					[
						50470,
						2,
						0,
						0
					],
					[
						50647,
						3,
						0,
						0
					]
				],
				"bpm": 0,
				"changeBPM": null,
				"mustHitSection": false
			},
			{
				"lengthInSteps": 16,
				"sectionNotes": [
					[
						50823.5294117647,
						0,
						0,
						""
					],
					[
						50911.7647058823,
						1,
						0,
						""
					],
					[
						51000.0000000004,
						0,
						0,
						""
					],
					[
						51088.2352941184,
						1,
						0,
						""
					],
					[
						51176.4705882354,
						0,
						0,
						""
					],
					[
						51264.7058823534,
						3,
						0,
						""
					],
					[
						51352.9411764714,
						0,
						0,
						""
					],
					[
						51441.1764705884,
						3,
						0,
						""
					],
					[
						51529.4117647064,
						1,
						0,
						""
					],
					[
						51617.6470588244,
						0,
						0,
						""
					],
					[
						51705.8823529414,
						1,
						0,
						""
					],
					[
						51794.1176470594,
						3,
						0,
						""
					],
					[
						51882.3529411764,
						1,
						0,
						""
					],
					[
						51970.5882352944,
						3,
						0,
						""
					],
					[
						52058.8235294124,
						1,
						0,
						""
					],
					[
						52147.0588235294,
						3,
						0,
						""
					]
				],
				"bpm": 0,
				"changeBPM": null,
				"mustHitSection": true
			},
			{
				"lengthInSteps": 16,
				"sectionNotes": [
					[
						52235.2941176474,
						2,
						0,
						""
					],
					[
						52323.5294117654,
						0,
						0,
						""
					],
					[
						52411.7647058824,
						1,
						0,
						""
					],
					[
						52500.0000000004,
						3,
						0,
						""
					],
					[
						52588.2352941177,
						2,
						0,
						""
					],
					[
						52676.4705882353,
						0,
						0,
						""
					],
					[
						52764.705882353,
						1,
						0,
						""
					],
					[
						52852.9411764706,
						3,
						0,
						""
					],
					[
						52941.1764705882,
						2,
						0,
						""
					],
					[
						53029.4117647059,
						1,
						0,
						""
					],
					[
						53117.6470588235,
						0,
						0,
						""
					],
					[
						53205.8823529412,
						1,
						0,
						""
					],
					[
						53294.1176470588,
						2,
						0,
						""
					],
					[
						53382.3529411765,
						3,
						0,
						""
					],
					[
						53470.5882352941,
						2,
						0,
						""
					],
					[
						53558.8235294118,
						1,
						0,
						""
					]
				],
				"bpm": 0,
				"changeBPM": null,
				"mustHitSection": true
			},
			{
				"lengthInSteps": 16,
				"sectionNotes": [
					[
						53647.0588235294,
						3,
						0,
						""
					],
					[
						53735.294117647,
						1,
						0,
						""
					],
					[
						53823.5294117647,
						3,
						0,
						""
					],
					[
						53911.7647058823,
						1,
						0,
						""
					],
					[
						54000,
						3,
						0,
						""
					],
					[
						54088.2352941176,
						0,
						0,
						""
					],
					[
						54176.4705882353,
						3,
						0,
						""
					],
					[
						54264.7058823529,
						0,
						0,
						""
					],
					[
						54352.9411764706,
						2,
						0,
						""
					],
					[
						54441.1764705882,
						0,
						0,
						""
					],
					[
						54529.4117647059,
						2,
						0,
						""
					],
					[
						54529.4117647059,
						5,
						0,
						""
					],
					[
						54617.6470588235,
						0,
						0,
						""
					],
					[
						54705.8823529411,
						3,
						0,
						""
					],
					[
						54705.8823529412,
						4,
						0,
						""
					],
					[
						54794.1176470588,
						0,
						0,
						""
					],
					[
						54882.3529411764,
						3,
						0,
						""
					],
					[
						54882.3529411765,
						4,
						0,
						""
					],
					[
						54970.5882352941,
						0,
						0,
						""
					]
				],
				"bpm": 0,
				"changeBPM": null,
				"mustHitSection": true
			},
			{
				"lengthInSteps": 16,
				"sectionNotes": [
					[
						55058.8235294118,
						3,
						0,
						""
					],
					[
						55058.8235294118,
						7,
						0,
						""
					],
					[
						55147.0588235291,
						2,
						0,
						""
					],
					[
						55235.2941176471,
						0,
						0,
						""
					],
					[
						55235.2941176471,
						7,
						0,
						""
					],
					[
						55323.5294117641,
						1,
						0,
						""
					],
					[
						55411.7647058821,
						3,
						0,
						""
					],
					[
						55411.7647058823,
						6,
						0,
						""
					],
					[
						55499.9999999994,
						2,
						0,
						""
					],
					[
						55588.235294117,
						0,
						0,
						""
					],
					[
						55588.2352941176,
						7,
						0,
						""
					],
					[
						55676.4705882347,
						1,
						0,
						""
					],
					[
						55764.7058823529,
						6,
						176.470588235294,
						""
					],
					[
						55764.7058823529,
						4,
						176.470588235294,
						""
					],
					[
						55764.7058823529,
						3,
						0,
						""
					],
					[
						55852.9411764705,
						2,
						0,
						""
					],
					[
						55941.1764705882,
						1,
						0,
						""
					],
					[
						56029.4117647058,
						0,
						0,
						""
					],
					[
						56117.6470588235,
						7,
						176.470588235294,
						""
					],
					[
						56117.6470588235,
						1,
						0,
						""
					],
					[
						56205.8823529411,
						2,
						0,
						""
					],
					[
						56294.1176470588,
						3,
						0,
						""
					],
					[
						56382.3529411764,
						2,
						0,
						""
					]
				],
				"bpm": 0,
				"changeBPM": null,
				"mustHitSection": true
			},
			{
				"lengthInSteps": 16,
				"sectionNotes": [
					[
						56470,
						5,
						264,
						0
					],
					[
						56470,
						0,
						0,
						0
					],
					[
						56558,
						1,
						0,
						0
					],
					[
						56647,
						0,
						0,
						0
					],
					[
						56735,
						1,
						0,
						0
					],
					[
						56823,
						0,
						0,
						0
					],
					[
						56911,
						3,
						0,
						0
					],
					[
						57000,
						0,
						0,
						0
					],
					[
						57088,
						3,
						0,
						0
					],
					[
						57176,
						1,
						0,
						0
					],
					[
						57264,
						0,
						0,
						0
					],
					[
						57352,
						1,
						0,
						0
					],
					[
						57441,
						3,
						0,
						0
					],
					[
						57529,
						1,
						0,
						0
					],
					[
						57617,
						3,
						0,
						0
					],
					[
						57705,
						1,
						0,
						0
					],
					[
						57794,
						3,
						0,
						0
					]
				],
				"bpm": 0,
				"changeBPM": null,
				"mustHitSection": false
			},
			{
				"lengthInSteps": 16,
				"sectionNotes": [
					[
						57882,
						2,
						0,
						0
					],
					[
						57970,
						3,
						0,
						0
					],
					[
						58058,
						2,
						0,
						0
					],
					[
						58147,
						0,
						0,
						0
					],
					[
						58235,
						3,
						0,
						0
					],
					[
						58279,
						2,
						0,
						0
					],
					[
						58323,
						1,
						0,
						0
					],
					[
						58367,
						0,
						0,
						0
					],
					[
						58411,
						2,
						0,
						0
					],
					[
						58588,
						1,
						0,
						0
					],
					[
						58764,
						0,
						0,
						0
					],
					[
						58852,
						1,
						0,
						0
					],
					[
						58941,
						0,
						0,
						0
					],
					[
						59117,
						1,
						0,
						0
					]
				],
				"bpm": 0,
				"changeBPM": null,
				"mustHitSection": false
			},
			{
				"lengthInSteps": 16,
				"sectionNotes": [
					[
						59294,
						3,
						0,
						0
					],
					[
						59382,
						0,
						0,
						0
					],
					[
						59470,
						3,
						0,
						0
					],
					[
						59558,
						0,
						0,
						0
					],
					[
						59647,
						3,
						0,
						0
					],
					[
						59735,
						3,
						0,
						0
					],
					[
						59823,
						2,
						0,
						0
					],
					[
						59911,
						0,
						0,
						0
					],
					[
						60000,
						2,
						0,
						0
					],
					[
						60088,
						2,
						0,
						0
					],
					[
						60176,
						0,
						0,
						0
					],
					[
						60264,
						1,
						0,
						0
					],
					[
						60352,
						0,
						0,
						0
					],
					[
						60441,
						3,
						0,
						0
					],
					[
						60529,
						0,
						0,
						0
					],
					[
						60617,
						1,
						0,
						0
					]
				],
				"bpm": 0,
				"changeBPM": null,
				"mustHitSection": false
			},
			{
				"lengthInSteps": 16,
				"sectionNotes": [
					[
						60705,
						0,
						0,
						0
					],
					[
						60794,
						2,
						0,
						0
					],
					[
						60882,
						0,
						0,
						0
					],
					[
						60970,
						1,
						0,
						0
					],
					[
						61058,
						3,
						0,
						0
					],
					[
						61102,
						0,
						0,
						0
					],
					[
						61147,
						1,
						0,
						0
					],
					[
						61191,
						2,
						0,
						0
					],
					[
						61235,
						3,
						0,
						0
					],
					[
						61411,
						2,
						0,
						0
					],
					[
						61588,
						0,
						0,
						0
					],
					[
						61676,
						3,
						0,
						0
					],
					[
						61764,
						2,
						0,
						0
					],
					[
						61941,
						3,
						0,
						0
					]
				],
				"bpm": 0,
				"changeBPM": null,
				"mustHitSection": false
			},
			{
				"lengthInSteps": 16,
				"sectionNotes": [
					[
						62117.6470588235,
						0,
						0,
						""
					],
					[
						62205.8823529411,
						1,
						0,
						""
					],
					[
						62294.1176470592,
						0,
						0,
						""
					],
					[
						62382.3529411772,
						1,
						0,
						""
					],
					[
						62470.5882352942,
						0,
						0,
						""
					],
					[
						62558.8235294122,
						3,
						0,
						""
					],
					[
						62647.0588235302,
						0,
						0,
						""
					],
					[
						62735.2941176472,
						3,
						0,
						""
					],
					[
						62823.5294117652,
						1,
						0,
						""
					],
					[
						62911.7647058832,
						0,
						0,
						""
					],
					[
						63000.0000000002,
						1,
						0,
						""
					],
					[
						63088.2352941182,
						3,
						0,
						""
					],
					[
						63176.4705882352,
						1,
						0,
						""
					],
					[
						63264.7058823532,
						3,
						0,
						""
					],
					[
						63352.9411764712,
						1,
						0,
						""
					],
					[
						63441.1764705882,
						3,
						0,
						""
					]
				],
				"bpm": 0,
				"changeBPM": null,
				"mustHitSection": true
			},
			{
				"lengthInSteps": 16,
				"sectionNotes": [
					[
						63529.4117647062,
						2,
						0,
						""
					],
					[
						63617.6470588242,
						0,
						0,
						""
					],
					[
						63705.8823529412,
						1,
						0,
						""
					],
					[
						63794.1176470592,
						3,
						0,
						""
					],
					[
						63882.3529411765,
						2,
						0,
						""
					],
					[
						63970.5882352941,
						0,
						0,
						""
					],
					[
						64058.8235294118,
						1,
						0,
						""
					],
					[
						64147.0588235294,
						3,
						0,
						""
					],
					[
						64235.2941176471,
						2,
						0,
						""
					],
					[
						64323.5294117647,
						1,
						0,
						""
					],
					[
						64411.7647058823,
						0,
						0,
						""
					],
					[
						64500,
						1,
						0,
						""
					],
					[
						64588.2352941176,
						2,
						0,
						""
					],
					[
						64676.4705882353,
						3,
						0,
						""
					],
					[
						64764.7058823529,
						2,
						0,
						""
					],
					[
						64852.9411764706,
						1,
						0,
						""
					]
				],
				"bpm": 0,
				"changeBPM": null,
				"mustHitSection": true
			},
			{
				"lengthInSteps": 16,
				"sectionNotes": [
					[
						64941.1764705882,
						3,
						0,
						""
					],
					[
						65029.4117647059,
						1,
						0,
						""
					],
					[
						65117.6470588242,
						3,
						0,
						""
					],
					[
						65205.8823529411,
						1,
						0,
						""
					],
					[
						65294.1176470592,
						3,
						0,
						""
					],
					[
						65382.3529411764,
						0,
						0,
						""
					],
					[
						65470.5882352942,
						3,
						0,
						""
					],
					[
						65558.8235294117,
						0,
						0,
						""
					],
					[
						65647.0588235294,
						2,
						0,
						""
					],
					[
						65735.2941176471,
						0,
						0,
						""
					],
					[
						65823.5294117647,
						2,
						0,
						""
					],
					[
						65911.7647058823,
						0,
						0,
						""
					],
					[
						66000,
						3,
						0,
						""
					],
					[
						66088.2352941177,
						0,
						0,
						""
					],
					[
						66176.4705882353,
						3,
						0,
						""
					],
					[
						66264.7058823529,
						0,
						0,
						""
					]
				],
				"bpm": 0,
				"changeBPM": null,
				"mustHitSection": true
			},
			{
				"lengthInSteps": 16,
				"sectionNotes": [
					[
						66352.9411764706,
						3,
						0,
						""
					],
					[
						66441.1764705882,
						2,
						0,
						""
					],
					[
						66529.4117647063,
						0,
						0,
						""
					],
					[
						66617.6470588232,
						1,
						0,
						""
					],
					[
						66705.8823529412,
						3,
						0,
						""
					],
					[
						66794.1176470585,
						2,
						0,
						""
					],
					[
						66882.3529411762,
						0,
						0,
						""
					],
					[
						66970.5882352938,
						1,
						0,
						""
					],
					[
						67058.8235294118,
						2,
						0,
						""
					],
					[
						67147.0588235294,
						3,
						0,
						""
					],
					[
						67235.2941176471,
						2,
						0,
						""
					],
					[
						67323.5294117647,
						0,
						0,
						""
					],
					[
						67411.7647058823,
						1,
						0,
						""
					],
					[
						67500,
						3,
						0,
						""
					],
					[
						67588.2352941177,
						2,
						0,
						""
					],
					[
						67676.4705882353,
						0,
						0,
						""
					]
				],
				"bpm": 0,
				"changeBPM": null,
				"mustHitSection": true
			},
			{
				"lengthInSteps": 16,
				"sectionNotes": [
					[
						67764,
						6,
						264,
						0
					],
					[
						67941,
						0,
						0,
						0
					],
					[
						68117,
						2,
						0,
						0
					],
					[
						68470,
						3,
						0,
						0
					],
					[
						68647,
						3,
						0,
						0
					],
					[
						68823,
						1,
						176,
						0
					]
				],
				"bpm": 0,
				"changeBPM": null,
				"mustHitSection": false
			},
			{
				"lengthInSteps": 16,
				"sectionNotes": [
					[
						69176,
						2,
						0,
						0
					],
					[
						69529,
						3,
						0,
						0
					],
					[
						69882,
						2,
						0,
						0
					],
					[
						70235,
						0,
						0,
						0
					],
					[
						70411,
						3,
						0,
						0
					]
				],
				"bpm": 0,
				"changeBPM": null,
				"mustHitSection": false
			},
			{
				"lengthInSteps": 16,
				"sectionNotes": [
					[
						70764,
						0,
						0,
						0
					],
					[
						70941,
						2,
						0,
						0
					],
					[
						71294,
						3,
						0,
						0
					],
					[
						71470,
						3,
						0,
						0
					],
					[
						71647,
						1,
						176,
						0
					]
				],
				"bpm": 0,
				"changeBPM": null,
				"mustHitSection": false
			},
			{
				"lengthInSteps": 16,
				"sectionNotes": [
					[
						71999,
						0,
						176,
						0
					],
					[
						72352,
						1,
						0,
						0
					],
					[
						72705,
						3,
						0,
						0
					],
					[
						72794,
						3,
						0,
						0
					],
					[
						72882,
						1,
						0,
						0
					],
					[
						73058,
						2,
						0,
						0
					],
					[
						73235,
						3,
						0,
						0
					]
				],
				"bpm": 0,
				"changeBPM": null,
				"mustHitSection": false
			},
			{
				"lengthInSteps": 16,
				"sectionNotes": [
					[
						73941.1764705882,
						0,
						88.2352941176359,
						""
					],
					[
						73411.7647058823,
						3,
						0,
						""
					],
					[
						73500,
						1,
						0,
						""
					],
					[
						73588.2352941176,
						3,
						0,
						""
					],
					[
						73764.7058823529,
						1,
						0,
						""
					],
					[
						73852.9411764706,
						2,
						0,
						""
					],
					[
						74117.6470588235,
						3,
						0,
						""
					],
					[
						74205.8823529412,
						1,
						0,
						""
					],
					[
						74294.1176470588,
						2,
						0,
						""
					],
					[
						74382.3529411765,
						3,
						0,
						""
					],
					[
						74470.5882352941,
						1,
						0,
						""
					],
					[
						74558.8235294118,
						0,
						0,
						""
					],
					[
						74647.0588235294,
						1,
						0,
						""
					],
					[
						74735.2941176471,
						3,
						0,
						""
					]
				],
				"bpm": 0,
				"changeBPM": null,
				"mustHitSection": true
			},
			{
				"lengthInSteps": 16,
				"sectionNotes": [
					[
						76058.8235294117,
						3,
						88.2352941176359,
						""
					],
					[
						75882.3529411764,
						2,
						88.2352941176505,
						""
					],
					[
						74823.5294117647,
						2,
						0,
						""
					],
					[
						74911.7647058823,
						1,
						0,
						""
					],
					[
						75000,
						0,
						0,
						""
					],
					[
						75088.2352941177,
						2,
						0,
						""
					],
					[
						75176.4705882353,
						3,
						0,
						""
					],
					[
						75264.7058823529,
						2,
						0,
						""
					],
					[
						75352.9411764706,
						1,
						0,
						""
					],
					[
						75441.1764705882,
						0,
						0,
						""
					],
					[
						75529.4117647059,
						2,
						0,
						""
					],
					[
						75617.6470588235,
						3,
						0,
						""
					],
					[
						75705.8823529412,
						1,
						0,
						""
					],
					[
						75794.1176470588,
						0,
						0,
						""
					]
				],
				"bpm": 0,
				"changeBPM": null,
				"mustHitSection": true
			},
			{
				"lengthInSteps": 16,
				"sectionNotes": [
					[
						77294.1176470587,
						1,
						88.2352941176505,
						""
					],
					[
						76411.7647058824,
						0,
						0,
						""
					],
					[
						76588.2352941176,
						2,
						0,
						""
					],
					[
						76941.1764705882,
						3,
						0,
						""
					],
					[
						77117.6470588235,
						3,
						0,
						""
					]
				],
				"bpm": 0,
				"changeBPM": null,
				"mustHitSection": true
			},
			{
				"lengthInSteps": 16,
				"sectionNotes": [
					[
						77647.0588235294,
						0,
						0,
						""
					],
					[
						77735.2941176471,
						2,
						0,
						""
					],
					[
						77823.5294117647,
						3,
						0,
						""
					],
					[
						77911.7647058824,
						2,
						0,
						""
					],
					[
						78000,
						0,
						0,
						""
					],
					[
						78088.2352941177,
						2,
						0,
						""
					],
					[
						78176.4705882353,
						3,
						0,
						""
					],
					[
						78264.705882353,
						2,
						0,
						""
					],
					[
						78352.9411764706,
						0,
						0,
						""
					],
					[
						78441.1764705883,
						3,
						0,
						""
					],
					[
						78529.4117647059,
						1,
						0,
						""
					],
					[
						78705.8823529412,
						2,
						0,
						""
					],
					[
						78882.3529411765,
						3,
						0,
						""
					],
					[
						78926.4705882353,
						2,
						0,
						""
					],
					[
						78970.5882352941,
						1,
						0,
						""
					],
					[
						79014.7058823529,
						0,
						0,
						""
					]
				],
				"bpm": 0,
				"changeBPM": null,
				"mustHitSection": true
			},
			{
				"lengthInSteps": 16,
				"sectionNotes": [
					[
						79235,
						0,
						0,
						0
					],
					[
						79323,
						0,
						0,
						0
					],
					[
						79411,
						2,
						0,
						0
					],
					[
						79764,
						3,
						0,
						0
					],
					[
						79941,
						3,
						0,
						0
					],
					[
						80117,
						1,
						176,
						0
					]
				],
				"bpm": 0,
				"changeBPM": null,
				"mustHitSection": false
			},
			{
				"lengthInSteps": 16,
				"sectionNotes": [
					[
						80470,
						2,
						0,
						0
					],
					[
						80823,
						3,
						0,
						0
					],
					[
						81176,
						2,
						0,
						0
					],
					[
						81529,
						0,
						0,
						0
					],
					[
						81705,
						3,
						0,
						0
					]
				],
				"bpm": 0,
				"changeBPM": null,
				"mustHitSection": false
			},
			{
				"lengthInSteps": 16,
				"sectionNotes": [
					[
						82058,
						0,
						0,
						0
					],
					[
						82235,
						2,
						0,
						0
					],
					[
						82588,
						3,
						0,
						0
					],
					[
						82764,
						3,
						0,
						0
					],
					[
						82941,
						1,
						176,
						0
					]
				],
				"bpm": 0,
				"changeBPM": null,
				"mustHitSection": false
			},
			{
				"lengthInSteps": 16,
				"sectionNotes": [
					[
						83294,
						0,
						176,
						0
					],
					[
						83647,
						1,
						0,
						0
					],
					[
						84000,
						3,
						0,
						0
					],
					[
						84088,
						3,
						0,
						0
					],
					[
						84176,
						1,
						0,
						0
					],
					[
						84352,
						2,
						0,
						0
					],
					[
						84529,
						3,
						0,
						0
					]
				],
				"bpm": 0,
				"changeBPM": null,
				"mustHitSection": false
			},
			{
				"lengthInSteps": 16,
				"sectionNotes": [
					[
						84705.8823529412,
						0,
						0,
						""
					],
					[
						84794.1176470588,
						1,
						0,
						""
					],
					[
						84882.3529411769,
						0,
						0,
						""
					],
					[
						84970.5882352949,
						1,
						0,
						""
					],
					[
						85058.8235294119,
						0,
						0,
						""
					],
					[
						85147.0588235299,
						3,
						0,
						""
					],
					[
						85235.2941176479,
						0,
						0,
						""
					],
					[
						85323.5294117649,
						3,
						0,
						""
					],
					[
						85411.7647058829,
						1,
						0,
						""
					],
					[
						85500.0000000009,
						0,
						0,
						""
					],
					[
						85588.2352941179,
						1,
						0,
						""
					],
					[
						85676.4705882359,
						3,
						0,
						""
					],
					[
						85764.7058823529,
						1,
						0,
						""
					],
					[
						85852.9411764709,
						3,
						0,
						""
					],
					[
						85941.1764705889,
						1,
						0,
						""
					],
					[
						86029.4117647059,
						3,
						0,
						""
					]
				],
				"bpm": 0,
				"changeBPM": null,
				"mustHitSection": true
			},
			{
				"lengthInSteps": 16,
				"sectionNotes": [
					[
						86117.6470588239,
						2,
						0,
						""
					],
					[
						86205.8823529419,
						0,
						0,
						""
					],
					[
						86294.1176470589,
						1,
						0,
						""
					],
					[
						86382.3529411769,
						3,
						0,
						""
					],
					[
						86470.5882352942,
						2,
						0,
						""
					],
					[
						86558.8235294118,
						0,
						0,
						""
					],
					[
						86647.0588235295,
						1,
						0,
						""
					],
					[
						86735.2941176471,
						3,
						0,
						""
					],
					[
						86823.5294117647,
						2,
						0,
						""
					],
					[
						86911.7647058824,
						1,
						0,
						""
					],
					[
						87000,
						0,
						0,
						""
					],
					[
						87088.2352941177,
						1,
						0,
						""
					],
					[
						87176.4705882353,
						2,
						0,
						""
					],
					[
						87264.705882353,
						3,
						0,
						""
					],
					[
						87352.9411764706,
						2,
						0,
						""
					],
					[
						87441.1764705883,
						1,
						0,
						""
					]
				],
				"bpm": 0,
				"changeBPM": null,
				"mustHitSection": true
			},
			{
				"lengthInSteps": 16,
				"sectionNotes": [
					[
						87529.4117647059,
						3,
						0,
						""
					],
					[
						87617.6470588235,
						1,
						0,
						""
					],
					[
						87705.8823529412,
						3,
						0,
						""
					],
					[
						87794.1176470588,
						1,
						0,
						""
					],
					[
						87882.3529411765,
						3,
						0,
						""
					],
					[
						87970.5882352941,
						0,
						0,
						""
					],
					[
						88058.8235294118,
						3,
						0,
						""
					],
					[
						88147.0588235294,
						0,
						0,
						""
					],
					[
						88235.2941176471,
						2,
						0,
						""
					],
					[
						88323.5294117647,
						0,
						0,
						""
					],
					[
						88411.7647058824,
						2,
						0,
						""
					],
					[
						88500,
						0,
						0,
						""
					],
					[
						88588.2352941176,
						3,
						0,
						""
					],
					[
						88676.4705882353,
						0,
						0,
						""
					],
					[
						88764.7058823529,
						3,
						0,
						""
					],
					[
						88852.9411764706,
						0,
						0,
						""
					]
				],
				"bpm": 0,
				"changeBPM": null,
				"mustHitSection": true
			},
			{
				"lengthInSteps": 16,
				"sectionNotes": [
					[
						88941.1764705882,
						3,
						0,
						""
					],
					[
						89029.4117647055,
						2,
						0,
						""
					],
					[
						89117.6470588235,
						0,
						0,
						""
					],
					[
						89205.8823529405,
						1,
						0,
						""
					],
					[
						89294.1176470585,
						3,
						0,
						""
					],
					[
						89382.3529411758,
						2,
						0,
						""
					],
					[
						89470.5882352934,
						0,
						0,
						""
					],
					[
						89558.8235294111,
						1,
						0,
						""
					],
					[
						89647.0588235293,
						3,
						0,
						""
					],
					[
						89735.2941176469,
						2,
						0,
						""
					],
					[
						89823.5294117646,
						1,
						0,
						""
					],
					[
						89911.7647058822,
						0,
						0,
						""
					],
					[
						89999.9999999999,
						1,
						0,
						""
					],
					[
						90088.2352941175,
						2,
						0,
						""
					],
					[
						90176.4705882352,
						3,
						0,
						""
					],
					[
						90264.7058823528,
						2,
						0,
						""
					]
				],
				"bpm": 0,
				"changeBPM": null,
				"mustHitSection": true
			},
			{
				"lengthInSteps": 16,
				"sectionNotes": [
					[
						90352.9411764706,
						1,
						970.588235294118,
						""
					]
				],
				"bpm": 0,
				"changeBPM": null,
				"mustHitSection": true
			},
			{
				"lengthInSteps": 16,
				"sectionNotes": [],
				"bpm": 0,
				"changeBPM": false,
				"mustHitSection": true
			},
			{
				"lengthInSteps": 16,
				"sectionNotes": [],
				"bpm": 0,
				"changeBPM": false,
				"mustHitSection": true
			},
			{
				"lengthInSteps": 16,
				"sectionNotes": [],
				"bpm": 0,
				"changeBPM": false,
				"mustHitSection": true
			},
			{
				"lengthInSteps": 16,
				"sectionNotes": [],
				"bpm": 0,
				"changeBPM": false,
				"mustHitSection": true
			},
			{
				"lengthInSteps": 16,
				"sectionNotes": [],
				"bpm": 170,
				"changeBPM": false,
				"mustHitSection": true
			}
		],
		"gf": "Gf",
		"bpm": 170,
		"song": "Blammed-Erect"
	}
}