{
    "song": {
        "speed": "2.1",
        "stage": "StageErect",
        "player1": "PicoPlayer",
        "player2": "Dad",
        "gf": "Nene",
        "song": "Dadbattle-Pico",
        "bpm": 180,
        "notes": [
            {
                "lengthInSteps": 16,
                "sectionNotes": [],
                "bpm": 0,
                "changeBPM": null,
                "mustHitSection": true
            },
            {
                "lengthInSteps": 16,
                "sectionNotes": [],
                "bpm": 0,
                "changeBPM": null,
                "mustHitSection": true
            },
            {
                "lengthInSteps": 16,
                "sectionNotes": [],
                "bpm": 0,
                "changeBPM": null,
                "mustHitSection": true
            },
            {
                "lengthInSteps": 16,
                "sectionNotes": [],
                "bpm": 0,
                "changeBPM": null,
                "mustHitSection": true
            },
            {
                "lengthInSteps": 16,
                "sectionNotes": [],
                "bpm": 0,
                "changeBPM": null,
                "mustHitSection": true
            },
            {
                "lengthInSteps": 16,
                "sectionNotes": [],
                "bpm": 0,
                "changeBPM": null,
                "mustHitSection": true
            },
            {
                "lengthInSteps": 16,
                "sectionNotes": [],
                "bpm": 0,
                "changeBPM": null,
                "mustHitSection": true
            },
            {
                "lengthInSteps": 16,
                "sectionNotes": [],
                "bpm": 0,
                "changeBPM": null,
                "mustHitSection": true
            },
            {
                "lengthInSteps": 16,
                "sectionNotes": [
                    [
                        10666.6666666667,
                        6,
                        0,
                        ""
                    ],
                    [
                        11000,
                        0,
                        0,
                        ""
                    ],
                    [
                        11000,
                        4,
                        0,
                        ""
                    ],
                    [
                        11166.6666666667,
                        2,
                        0,
                        ""
                    ],
                    [
                        11166.6666666667,
                        5,
                        0,
                        ""
                    ],
                    [
                        11333.3333333333,
                        1,
                        0,
                        ""
                    ],
                    [
                        11333.3333333333,
                        6,
                        0,
                        ""
                    ],
                    [
                        11666.6666666667,
                        3,
                        0,
                        ""
                    ],
                    [
                        11666.6666666667,
                        4,
                        0,
                        ""
                    ],
                    [
                        11833.3333333333,
                        1,
                        0,
                        ""
                    ],
                    [
                        11833.3333333333,
                        7,
                        0,
                        ""
                    ]
                ],
                "bpm": 0,
                "changeBPM": null,
                "mustHitSection": true
            },
            {
                "lengthInSteps": 16,
                "sectionNotes": [
                    [
                        12000,
                        2,
                        0,
                        ""
                    ],
                    [
                        12000,
                        6,
                        0,
                        ""
                    ],
                    [
                        12166.6666666667,
                        0,
                        0,
                        ""
                    ],
                    [
                        12166.6666666667,
                        7,
                        0,
                        ""
                    ],
                    [
                        12333.3333333333,
                        4,
                        0,
                        ""
                    ],
                    [
                        12333.3333333333,
                        1,
                        0,
                        ""
                    ],
                    [
                        12500,
                        2,
                        0,
                        ""
                    ],
                    [
                        12527.7777777778,
                        5,
                        0,
                        ""
                    ],
                    [
                        12666.6666666667,
                        3,
                        83,
                        ""
                    ],
                    [
                        12694.4444444444,
                        6,
                        0,
                        ""
                    ],
                    [
                        13000,
                        0,
                        0,
                        ""
                    ],
                    [
                        13000,
                        4,
                        0,
                        ""
                    ],
                    [
                        13166.6666666667,
                        1,
                        0,
                        ""
                    ],
                    [
                        13166.6666666667,
                        7,
                        0,
                        ""
                    ]
                ],
                "bpm": 0,
                "changeBPM": null,
                "mustHitSection": true
            },
            {
                "lengthInSteps": 16,
                "sectionNotes": [
                    [
                        13333.3333333333,
                        0,
                        0,
                        ""
                    ],
                    [
                        13500,
                        3,
                        0,
                        ""
                    ],
                    [
                        13666.6666666667,
                        2,
                        0,
                        ""
                    ],
                    [
                        13833.3333333333,
                        1,
                        0,
                        ""
                    ],
                    [
                        14000,
                        0,
                        83,
                        ""
                    ],
                    [
                        14333.3333333333,
                        1,
                        0,
                        ""
                    ],
                    [
                        14500,
                        1,
                        0,
                        ""
                    ]
                ],
                "bpm": 0,
                "changeBPM": null,
                "mustHitSection": true
            },
            {
                "lengthInSteps": 16,
                "sectionNotes": [
                    [
                        14666.6666666667,
                        0,
                        0,
                        ""
                    ],
                    [
                        14833.3333333333,
                        2,
                        0,
                        ""
                    ],
                    [
                        15000,
                        1,
                        0,
                        ""
                    ],
                    [
                        15166.6666666667,
                        3,
                        0,
                        ""
                    ],
                    [
                        15333.3333333333,
                        0,
                        0,
                        ""
                    ],
                    [
                        15666.6666666667,
                        2,
                        0,
                        ""
                    ],
                    [
                        15833.3333333333,
                        0,
                        0,
                        ""
                    ],
                    [
                        15916.6666666667,
                        3,
                        0,
                        ""
                    ]
                ],
                "bpm": 0,
                "changeBPM": null,
                "mustHitSection": true
            },
            {
                "lengthInSteps": 16,
                "sectionNotes": [
                    [
                        16000,
                        5,
                        0,
                        ""
                    ],
                    [
                        16333.3333333333,
                        4,
                        0,
                        ""
                    ],
                    [
                        16500,
                        7,
                        0,
                        ""
                    ],
                    [
                        16666.6666666667,
                        5,
                        0,
                        ""
                    ],
                    [
                        17000,
                        6,
                        0,
                        ""
                    ]
                ],
                "bpm": 0,
                "changeBPM": null,
                "mustHitSection": true
            },
            {
                "lengthInSteps": 16,
                "sectionNotes": [
                    [
                        17333.3333333333,
                        5,
                        0,
                        ""
                    ],
                    [
                        17666.6666666667,
                        4,
                        0,
                        ""
                    ],
                    [
                        17833.3333333333,
                        4,
                        0,
                        ""
                    ],
                    [
                        18000,
                        7,
                        0,
                        ""
                    ],
                    [
                        18166.6666666667,
                        7,
                        0,
                        ""
                    ],
                    [
                        18333.3333333333,
                        3,
                        0,
                        ""
                    ],
                    [
                        18333.3333333333,
                        7,
                        0,
                        ""
                    ],
                    [
                        18500,
                        3,
                        0,
                        ""
                    ],
                    [
                        18500,
                        7,
                        0,
                        ""
                    ]
                ],
                "bpm": 0,
                "changeBPM": null,
                "mustHitSection": true
            },
            {
                "lengthInSteps": 16,
                "sectionNotes": [
                    [
                        18666.6666666667,
                        0,
                        167,
                        ""
                    ],
                    [
                        19000,
                        1,
                        167,
                        ""
                    ],
                    [
                        19333.3333333333,
                        3,
                        167,
                        ""
                    ],
                    [
                        19666.6666666667,
                        1,
                        0,
                        ""
                    ],
                    [
                        19833.3333333333,
                        3,
                        0,
                        ""
                    ]
                ],
                "bpm": 0,
                "changeBPM": null,
                "mustHitSection": true
            },
            {
                "lengthInSteps": 16,
                "sectionNotes": [
                    [
                        20000,
                        0,
                        0,
                        ""
                    ],
                    [
                        20166.6666666667,
                        0,
                        0,
                        ""
                    ],
                    [
                        20333.3333333333,
                        2,
                        0,
                        ""
                    ],
                    [
                        20500,
                        0,
                        0,
                        ""
                    ],
                    [
                        20666.6666666667,
                        2,
                        0,
                        ""
                    ],
                    [
                        20666.6666666667,
                        3,
                        0,
                        ""
                    ],
                    [
                        20833.3333333333,
                        1,
                        0,
                        ""
                    ],
                    [
                        21000,
                        3,
                        0,
                        ""
                    ],
                    [
                        21166.6666666667,
                        0,
                        0,
                        ""
                    ]
                ],
                "bpm": 0,
                "changeBPM": null,
                "mustHitSection": true
            },
            {
                "lengthInSteps": 16,
                "sectionNotes": [
                    [
                        21666.6666666667,
                        1,
                        0,
                        ""
                    ],
                    [
                        21666.6666666667,
                        6,
                        0,
                        ""
                    ],
                    [
                        21833.3333333333,
                        0,
                        0,
                        ""
                    ],
                    [
                        21833.3333333333,
                        5,
                        0,
                        ""
                    ],
                    [
                        22000,
                        7,
                        583,
                        ""
                    ],
                    [
                        22166.6666666667,
                        2,
                        0,
                        ""
                    ],
                    [
                        22333.3333333333,
                        1,
                        0,
                        ""
                    ]
                ],
                "bpm": 0,
                "changeBPM": null,
                "mustHitSection": true
            },
            {
                "lengthInSteps": 16,
                "sectionNotes": [
                    [
                        22666.6666666667,
                        3,
                        0,
                        ""
                    ],
                    [
                        22666.6666666667,
                        2,
                        83,
                        ""
                    ],
                    [
                        22833.3333333333,
                        5,
                        0,
                        ""
                    ],
                    [
                        23000,
                        1,
                        0,
                        ""
                    ],
                    [
                        23000,
                        7,
                        0,
                        ""
                    ],
                    [
                        23166.6666666667,
                        2,
                        0,
                        ""
                    ],
                    [
                        23333.3333333333,
                        4,
                        583,
                        ""
                    ],
                    [
                        23500,
                        0,
                        0,
                        ""
                    ],
                    [
                        23666.6666666667,
                        2,
                        0,
                        ""
                    ]
                ],
                "bpm": 0,
                "changeBPM": null,
                "mustHitSection": true
            },
            {
                "lengthInSteps": 16,
                "sectionNotes": [
                    [
                        24000,
                        0,
                        0,
                        ""
                    ],
                    [
                        24000,
                        1,
                        167,
                        ""
                    ],
                    [
                        24333.3333333333,
                        0,
                        0,
                        ""
                    ],
                    [
                        24333.3333333333,
                        6,
                        0,
                        ""
                    ],
                    [
                        24500,
                        2,
                        0,
                        ""
                    ],
                    [
                        24666.6666666667,
                        5,
                        0,
                        ""
                    ],
                    [
                        24833.3333333333,
                        0,
                        0,
                        ""
                    ],
                    [
                        25000,
                        1,
                        0,
                        ""
                    ],
                    [
                        25000,
                        4,
                        0,
                        ""
                    ],
                    [
                        25166.6666666667,
                        2,
                        0,
                        ""
                    ],
                    [
                        25166.6666666667,
                        5,
                        0,
                        ""
                    ]
                ],
                "bpm": 0,
                "changeBPM": null,
                "mustHitSection": true
            },
            {
                "lengthInSteps": 16,
                "sectionNotes": [
                    [
                        25333.3333333333,
                        6,
                        0,
                        ""
                    ],
                    [
                        25333.3333333333,
                        3,
                        167,
                        ""
                    ],
                    [
                        25500,
                        7,
                        0,
                        ""
                    ],
                    [
                        25666.6666666667,
                        1,
                        0,
                        ""
                    ],
                    [
                        25666.6666666667,
                        4,
                        0,
                        ""
                    ],
                    [
                        25833.3333333333,
                        7,
                        0,
                        ""
                    ],
                    [
                        25833.3333333333,
                        0,
                        0,
                        ""
                    ],
                    [
                        26000,
                        3,
                        167,
                        ""
                    ],
                    [
                        26000,
                        2,
                        0,
                        ""
                    ],
                    [
                        26000,
                        6,
                        0,
                        ""
                    ],
                    [
                        26333.3333333333,
                        3,
                        0,
                        ""
                    ],
                    [
                        26500,
                        0,
                        0,
                        ""
                    ]
                ],
                "bpm": 0,
                "changeBPM": null,
                "mustHitSection": true
            },
            {
                "lengthInSteps": 16,
                "sectionNotes": [
                    [
                        26666.6666666667,
                        2,
                        0,
                        ""
                    ],
                    [
                        26666.6666666667,
                        3,
                        0,
                        ""
                    ],
                    [
                        27000,
                        1,
                        0,
                        ""
                    ],
                    [
                        27166.6666666667,
                        0,
                        0,
                        ""
                    ],
                    [
                        27333.3333333333,
                        2,
                        0,
                        ""
                    ],
                    [
                        27500,
                        3,
                        0,
                        ""
                    ],
                    [
                        27666.6666666667,
                        0,
                        0,
                        ""
                    ],
                    [
                        27833.3333333333,
                        2,
                        0,
                        ""
                    ]
                ],
                "bpm": 0,
                "changeBPM": null,
                "mustHitSection": true
            },
            {
                "lengthInSteps": 16,
                "sectionNotes": [
                    [
                        28000,
                        0,
                        167,
                        ""
                    ],
                    [
                        28333.3333333333,
                        1,
                        0,
                        ""
                    ],
                    [
                        28500,
                        3,
                        0,
                        ""
                    ],
                    [
                        28666.6666666667,
                        1,
                        0,
                        ""
                    ],
                    [
                        28833.3333333333,
                        2,
                        0,
                        ""
                    ],
                    [
                        29000,
                        3,
                        0,
                        ""
                    ],
                    [
                        29166.6666666667,
                        1,
                        0,
                        ""
                    ]
                ],
                "bpm": 0,
                "changeBPM": null,
                "mustHitSection": true
            },
            {
                "lengthInSteps": 16,
                "sectionNotes": [
                    [
                        29333.3333333333,
                        0,
                        250,
                        ""
                    ],
                    [
                        29666.6666666667,
                        2,
                        0,
                        ""
                    ],
                    [
                        29833.3333333333,
                        0,
                        167,
                        ""
                    ],
                    [
                        30000,
                        1,
                        0,
                        ""
                    ],
                    [
                        30166.6666666667,
                        3,
                        0,
                        ""
                    ],
                    [
                        30333.3333333333,
                        1,
                        0,
                        ""
                    ]
                ],
                "bpm": 0,
                "changeBPM": null,
                "mustHitSection": true
            },
            {
                "lengthInSteps": 16,
                "sectionNotes": [
                    [
                        30666.6666666667,
                        3,
                        167,
                        ""
                    ],
                    [
                        30666.6666666667,
                        0,
                        167,
                        ""
                    ],
                    [
                        31000,
                        1,
                        0,
                        ""
                    ],
                    [
                        31333.3333333333,
                        2,
                        0,
                        ""
                    ],
                    [
                        31333.3333333333,
                        1,
                        0,
                        ""
                    ],
                    [
                        31666.6666666667,
                        1,
                        0,
                        ""
                    ],
                    [
                        31666.6666666667,
                        2,
                        0,
                        ""
                    ]
                ],
                "bpm": 0,
                "changeBPM": null,
                "mustHitSection": true
            },
            {
                "lengthInSteps": 16,
                "sectionNotes": [
                    [
                        32166.6666666667,
                        4,
                        0,
                        ""
                    ],
                    [
                        32333.3333333333,
                        7,
                        0,
                        ""
                    ],
                    [
                        32500,
                        6,
                        0,
                        ""
                    ],
                    [
                        32666.6666666667,
                        5,
                        0,
                        ""
                    ],
                    [
                        33000,
                        4,
                        0,
                        ""
                    ]
                ],
                "bpm": 0,
                "changeBPM": null,
                "mustHitSection": true
            },
            {
                "lengthInSteps": 16,
                "sectionNotes": [
                    [
                        33500,
                        6,
                        0,
                        ""
                    ],
                    [
                        33666.6666666667,
                        7,
                        0,
                        ""
                    ],
                    [
                        33833.3333333333,
                        5,
                        0,
                        ""
                    ],
                    [
                        34000,
                        6,
                        0,
                        ""
                    ],
                    [
                        34333.3333333333,
                        4,
                        0,
                        ""
                    ]
                ],
                "bpm": 0,
                "changeBPM": null,
                "mustHitSection": true
            },
            {
                "lengthInSteps": 16,
                "sectionNotes": [
                    [
                        34666.6666666667,
                        4,
                        0,
                        ""
                    ],
                    [
                        35000,
                        5,
                        0,
                        ""
                    ],
                    [
                        35333.3333333333,
                        7,
                        0,
                        ""
                    ],
                    [
                        35666.6666666667,
                        5,
                        0,
                        ""
                    ]
                ],
                "bpm": 0,
                "changeBPM": null,
                "mustHitSection": true
            },
            {
                "lengthInSteps": 16,
                "sectionNotes": [
                    [
                        36000,
                        6,
                        0,
                        ""
                    ],
                    [
                        36333.3333333333,
                        7,
                        0,
                        ""
                    ],
                    [
                        36666.6666666667,
                        4,
                        0,
                        ""
                    ],
                    [
                        36666.6666666667,
                        5,
                        0,
                        ""
                    ]
                ],
                "bpm": 0,
                "changeBPM": null,
                "mustHitSection": true
            },
            {
                "lengthInSteps": 16,
                "sectionNotes": [
                    [
                        37500,
                        5,
                        0,
                        ""
                    ],
                    [
                        37666.6666666667,
                        7,
                        0,
                        ""
                    ],
                    [
                        37833.3333333333,
                        6,
                        0,
                        ""
                    ],
                    [
                        38000,
                        4,
                        0,
                        ""
                    ],
                    [
                        38166.6666666667,
                        6,
                        0,
                        ""
                    ],
                    [
                        38333.3333333333,
                        5,
                        0,
                        ""
                    ]
                ],
                "bpm": 0,
                "changeBPM": null,
                "mustHitSection": true
            },
            {
                "lengthInSteps": 16,
                "sectionNotes": [
                    [
                        38666.6666666667,
                        4,
                        0,
                        ""
                    ],
                    [
                        38750,
                        7,
                        0,
                        ""
                    ],
                    [
                        38833.3333333333,
                        4,
                        0,
                        ""
                    ],
                    [
                        39000,
                        5,
                        0,
                        ""
                    ],
                    [
                        39166.6666666667,
                        4,
                        0,
                        ""
                    ],
                    [
                        39333.3333333333,
                        6,
                        0,
                        ""
                    ],
                    [
                        39500,
                        7,
                        0,
                        ""
                    ],
                    [
                        39666.6666666667,
                        5,
                        0,
                        ""
                    ]
                ],
                "bpm": 0,
                "changeBPM": null,
                "mustHitSection": true
            },
            {
                "lengthInSteps": 16,
                "sectionNotes": [
                    [
                        40166.6666666667,
                        4,
                        0,
                        ""
                    ],
                    [
                        40333.3333333333,
                        7,
                        0,
                        ""
                    ],
                    [
                        40500,
                        5,
                        0,
                        ""
                    ],
                    [
                        40666.6666666667,
                        6,
                        0,
                        ""
                    ],
                    [
                        40833.3333333333,
                        7,
                        0,
                        ""
                    ],
                    [
                        41000,
                        1,
                        0,
                        ""
                    ],
                    [
                        41000,
                        5,
                        0,
                        ""
                    ],
                    [
                        41166.6666666667,
                        3,
                        250,
                        ""
                    ],
                    [
                        41166.6666666667,
                        7,
                        0,
                        ""
                    ]
                ],
                "bpm": 0,
                "changeBPM": null,
                "mustHitSection": true
            },
            {
                "lengthInSteps": 16,
                "sectionNotes": [
                    [
                        41333.3333333333,
                        4,
                        0,
                        ""
                    ],
                    [
                        41500,
                        0,
                        0,
                        ""
                    ],
                    [
                        41500,
                        5,
                        0,
                        ""
                    ],
                    [
                        41666.6666666667,
                        2,
                        0,
                        ""
                    ],
                    [
                        41666.6666666667,
                        4,
                        0,
                        ""
                    ],
                    [
                        41833.3333333333,
                        1,
                        0,
                        ""
                    ],
                    [
                        41833.3333333333,
                        7,
                        0,
                        ""
                    ],
                    [
                        42000,
                        0,
                        0,
                        ""
                    ],
                    [
                        42000,
                        6,
                        0,
                        ""
                    ],
                    [
                        42166.6666666667,
                        3,
                        0,
                        ""
                    ],
                    [
                        42333.3333333333,
                        1,
                        0,
                        ""
                    ],
                    [
                        42333.3333333333,
                        7,
                        0,
                        ""
                    ],
                    [
                        42500,
                        2,
                        250,
                        ""
                    ]
                ],
                "bpm": 0,
                "changeBPM": null,
                "mustHitSection": true
            },
            {
                "lengthInSteps": 16,
                "sectionNotes": [
                    [
                        42666.6666666667,
                        5,
                        417,
                        ""
                    ],
                    [
                        42833.3333333333,
                        3,
                        0,
                        ""
                    ],
                    [
                        43000,
                        1,
                        0,
                        ""
                    ],
                    [
                        43166.6666666667,
                        0,
                        0,
                        ""
                    ],
                    [
                        43333.3333333333,
                        2,
                        0,
                        ""
                    ],
                    [
                        43500,
                        0,
                        0,
                        ""
                    ],
                    [
                        43666.6666666667,
                        3,
                        0,
                        ""
                    ],
                    [
                        43833.3333333333,
                        1,
                        0,
                        ""
                    ]
                ],
                "bpm": 0,
                "changeBPM": null,
                "mustHitSection": true
            },
            {
                "lengthInSteps": 16,
                "sectionNotes": [
                    [
                        44000,
                        3,
                        0,
                        ""
                    ],
                    [
                        44166.6666666667,
                        0,
                        0,
                        ""
                    ],
                    [
                        44333.3333333333,
                        2,
                        0,
                        ""
                    ],
                    [
                        44500,
                        3,
                        0,
                        ""
                    ],
                    [
                        44666.6666666667,
                        0,
                        0,
                        ""
                    ],
                    [
                        44833.3333333333,
                        2,
                        0,
                        ""
                    ],
                    [
                        45000,
                        0,
                        0,
                        ""
                    ],
                    [
                        45166.6666666667,
                        3,
                        0,
                        ""
                    ]
                ],
                "bpm": 0,
                "changeBPM": null,
                "mustHitSection": true
            },
            {
                "lengthInSteps": 16,
                "sectionNotes": [
                    [
                        45333.3333333333,
                        0,
                        0,
                        ""
                    ],
                    [
                        45500,
                        2,
                        0,
                        ""
                    ],
                    [
                        45666.6666666667,
                        0,
                        0,
                        ""
                    ],
                    [
                        45833.3333333333,
                        1,
                        0,
                        ""
                    ],
                    [
                        46000,
                        3,
                        0,
                        ""
                    ],
                    [
                        46166.6666666667,
                        0,
                        0,
                        ""
                    ],
                    [
                        46333.3333333333,
                        1,
                        0,
                        ""
                    ],
                    [
                        46500,
                        2,
                        83,
                        ""
                    ]
                ],
                "bpm": 0,
                "changeBPM": null,
                "mustHitSection": true
            },
            {
                "lengthInSteps": 16,
                "sectionNotes": [
                    [
                        46666.6666666667,
                        0,
                        0,
                        ""
                    ],
                    [
                        46833.3333333333,
                        0,
                        0,
                        ""
                    ],
                    [
                        47000,
                        2,
                        0,
                        ""
                    ],
                    [
                        47166.6666666667,
                        1,
                        0,
                        ""
                    ],
                    [
                        47333.3333333333,
                        3,
                        83,
                        ""
                    ],
                    [
                        47333.3333333333,
                        4,
                        250,
                        ""
                    ],
                    [
                        47666.6666666667,
                        1,
                        167,
                        ""
                    ],
                    [
                        47666.6666666667,
                        4,
                        250,
                        ""
                    ]
                ],
                "bpm": 0,
                "changeBPM": null,
                "mustHitSection": true
            },
            {
                "lengthInSteps": 16,
                "sectionNotes": [
                    [
                        48000,
                        0,
                        0,
                        ""
                    ],
                    [
                        48000,
                        6,
                        917,
                        ""
                    ],
                    [
                        48166.6666666667,
                        2,
                        0,
                        ""
                    ],
                    [
                        48333.3333333333,
                        1,
                        0,
                        ""
                    ],
                    [
                        48500,
                        0,
                        0,
                        ""
                    ],
                    [
                        48666.6666666667,
                        3,
                        0,
                        ""
                    ],
                    [
                        48833.3333333333,
                        1,
                        0,
                        ""
                    ],
                    [
                        48958.3333333333,
                        6,
                        833,
                        ""
                    ],
                    [
                        49000,
                        0,
                        0,
                        ""
                    ],
                    [
                        49166.6666666667,
                        2,
                        0,
                        ""
                    ],
                    [
                        49291.6666666667,
                        1,
                        0,
                        ""
                    ]
                ],
                "bpm": 0,
                "changeBPM": null,
                "mustHitSection": true
            },
            {
                "lengthInSteps": 16,
                "sectionNotes": [
                    [
                        49354.1666666667,
                        3,
                        0,
                        ""
                    ],
                    [
                        49500,
                        2,
                        0,
                        ""
                    ],
                    [
                        49666.6666666667,
                        1,
                        0,
                        ""
                    ],
                    [
                        49833.3333333333,
                        0,
                        0,
                        ""
                    ],
                    [
                        49875,
                        6,
                        1667,
                        ""
                    ],
                    [
                        50000,
                        3,
                        0,
                        ""
                    ],
                    [
                        50166.6666666667,
                        1,
                        0,
                        ""
                    ],
                    [
                        50333.3333333333,
                        0,
                        0,
                        ""
                    ],
                    [
                        50500,
                        2,
                        0,
                        ""
                    ],
                    [
                        50625,
                        1,
                        0,
                        ""
                    ]
                ],
                "bpm": 0,
                "changeBPM": null,
                "mustHitSection": true
            },
            {
                "lengthInSteps": 16,
                "sectionNotes": [
                    [
                        50687.5,
                        3,
                        0,
                        ""
                    ],
                    [
                        50833.3333333333,
                        0,
                        0,
                        ""
                    ],
                    [
                        51000,
                        2,
                        0,
                        ""
                    ],
                    [
                        51083.3333333333,
                        3,
                        0,
                        ""
                    ],
                    [
                        51250,
                        0,
                        0,
                        ""
                    ],
                    [
                        51333.3333333333,
                        3,
                        0,
                        ""
                    ],
                    [
                        51416.6666666667,
                        2,
                        0,
                        ""
                    ],
                    [
                        51583.3333333333,
                        0,
                        0,
                        ""
                    ],
                    [
                        51750,
                        1,
                        0,
                        ""
                    ],
                    [
                        51916.6666666667,
                        3,
                        0,
                        ""
                    ]
                ],
                "bpm": 0,
                "changeBPM": null,
                "mustHitSection": true
            },
            {
                "lengthInSteps": 16,
                "sectionNotes": [
                    [
                        52000,
                        2,
                        0,
                        ""
                    ],
                    [
                        52166.6666666667,
                        0,
                        0,
                        ""
                    ],
                    [
                        52333.3333333333,
                        1,
                        0,
                        ""
                    ],
                    [
                        52500,
                        2,
                        0,
                        ""
                    ],
                    [
                        52666.6666666667,
                        0,
                        0,
                        ""
                    ],
                    [
                        52833.3333333333,
                        3,
                        0,
                        ""
                    ],
                    [
                        53000,
                        2,
                        0,
                        ""
                    ],
                    [
                        53166.6666666667,
                        0,
                        0,
                        ""
                    ],
                    [
                        53250,
                        0,
                        0,
                        ""
                    ]
                ],
                "bpm": 0,
                "changeBPM": null,
                "mustHitSection": true
            },
            {
                "lengthInSteps": 16,
                "sectionNotes": [
                    [
                        53333.3333333333,
                        6,
                        0,
                        ""
                    ],
                    [
                        53666.6666666667,
                        4,
                        0,
                        ""
                    ],
                    [
                        53833.3333333333,
                        5,
                        0,
                        ""
                    ],
                    [
                        54000,
                        6,
                        0,
                        ""
                    ],
                    [
                        54333.3333333333,
                        4,
                        0,
                        ""
                    ],
                    [
                        54333.3333333334,
                        0,
                        0,
                        ""
                    ],
                    [
                        54500,
                        3,
                        0,
                        ""
                    ],
                    [
                        54500,
                        7,
                        0,
                        ""
                    ]
                ],
                "bpm": 0,
                "changeBPM": null,
                "mustHitSection": true
            },
            {
                "lengthInSteps": 16,
                "sectionNotes": [
                    [
                        54666.6666666667,
                        2,
                        0,
                        ""
                    ],
                    [
                        54666.6666666667,
                        6,
                        0,
                        ""
                    ],
                    [
                        54833.3333333333,
                        3,
                        0,
                        ""
                    ],
                    [
                        54833.3333333333,
                        7,
                        0,
                        ""
                    ],
                    [
                        55000,
                        0,
                        0,
                        ""
                    ],
                    [
                        55000,
                        4,
                        0,
                        ""
                    ],
                    [
                        55166.6666666667,
                        1,
                        0,
                        ""
                    ],
                    [
                        55166.6666666667,
                        5,
                        0,
                        ""
                    ],
                    [
                        55333.3333333333,
                        2,
                        83,
                        ""
                    ],
                    [
                        55333.3333333333,
                        6,
                        0,
                        ""
                    ],
                    [
                        55666.6666666667,
                        0,
                        0,
                        ""
                    ],
                    [
                        55666.6666666667,
                        4,
                        0,
                        ""
                    ],
                    [
                        55833.3333333333,
                        1,
                        0,
                        ""
                    ],
                    [
                        55833.3333333333,
                        7,
                        0,
                        ""
                    ]
                ],
                "bpm": 0,
                "changeBPM": null,
                "mustHitSection": true
            },
            {
                "lengthInSteps": 16,
                "sectionNotes": [
                    [
                        56000,
                        3,
                        0,
                        ""
                    ],
                    [
                        56166.6666666667,
                        2,
                        0,
                        ""
                    ],
                    [
                        56333.3333333334,
                        1,
                        0,
                        ""
                    ],
                    [
                        56500,
                        0,
                        0,
                        ""
                    ],
                    [
                        56666.6666666667,
                        3,
                        83,
                        ""
                    ],
                    [
                        57000,
                        0,
                        0,
                        ""
                    ],
                    [
                        57166.6666666667,
                        3,
                        0,
                        ""
                    ]
                ],
                "bpm": 0,
                "changeBPM": null,
                "mustHitSection": true
            },
            {
                "lengthInSteps": 16,
                "sectionNotes": [
                    [
                        57333.3333333333,
                        2,
                        0,
                        ""
                    ],
                    [
                        57500,
                        1,
                        0,
                        ""
                    ],
                    [
                        57666.6666666667,
                        0,
                        0,
                        ""
                    ],
                    [
                        57833.3333333333,
                        3,
                        0,
                        ""
                    ],
                    [
                        58000,
                        0,
                        83,
                        ""
                    ],
                    [
                        58333.3333333334,
                        0,
                        0,
                        ""
                    ],
                    [
                        58500,
                        1,
                        0,
                        ""
                    ],
                    [
                        58583.3333333333,
                        3,
                        0,
                        ""
                    ]
                ],
                "bpm": 0,
                "changeBPM": null,
                "mustHitSection": true
            },
            {
                "lengthInSteps": 16,
                "sectionNotes": [
                    [
                        58666.6666666667,
                        5,
                        0,
                        ""
                    ],
                    [
                        59000,
                        4,
                        0,
                        ""
                    ],
                    [
                        59166.6666666667,
                        7,
                        0,
                        ""
                    ],
                    [
                        59333.3333333333,
                        5,
                        0,
                        ""
                    ],
                    [
                        59666.6666666667,
                        6,
                        0,
                        ""
                    ]
                ],
                "bpm": 0,
                "changeBPM": null,
                "mustHitSection": true
            },
            {
                "lengthInSteps": 16,
                "sectionNotes": [
                    [
                        60000,
                        5,
                        0,
                        ""
                    ],
                    [
                        60333.3333333333,
                        4,
                        0,
                        ""
                    ],
                    [
                        60500,
                        4,
                        0,
                        ""
                    ],
                    [
                        60666.6666666667,
                        7,
                        0,
                        ""
                    ],
                    [
                        60833.3333333333,
                        7,
                        0,
                        ""
                    ],
                    [
                        61000,
                        1,
                        0,
                        ""
                    ],
                    [
                        61000,
                        7,
                        0,
                        ""
                    ],
                    [
                        61166.6666666667,
                        3,
                        0,
                        ""
                    ],
                    [
                        61166.6666666667,
                        7,
                        0,
                        ""
                    ]
                ],
                "bpm": 0,
                "changeBPM": null,
                "mustHitSection": true
            },
            {
                "lengthInSteps": 16,
                "sectionNotes": [
                    [
                        61333.3333333333,
                        2,
                        0,
                        ""
                    ],
                    [
                        61500,
                        1,
                        0,
                        ""
                    ],
                    [
                        61666.6666666667,
                        3,
                        0,
                        ""
                    ],
                    [
                        61833.3333333333,
                        1,
                        0,
                        ""
                    ],
                    [
                        62000,
                        0,
                        0,
                        ""
                    ],
                    [
                        62166.6666666667,
                        1,
                        0,
                        ""
                    ],
                    [
                        62333.3333333333,
                        2,
                        0,
                        ""
                    ],
                    [
                        62500,
                        2,
                        0,
                        ""
                    ]
                ],
                "bpm": 0,
                "changeBPM": null,
                "mustHitSection": true
            },
            {
                "lengthInSteps": 16,
                "sectionNotes": [
                    [
                        62666.6666666667,
                        3,
                        0,
                        ""
                    ],
                    [
                        62833.3333333333,
                        1,
                        0,
                        ""
                    ],
                    [
                        63000,
                        0,
                        0,
                        ""
                    ],
                    [
                        63166.6666666667,
                        1,
                        0,
                        ""
                    ],
                    [
                        63333.3333333333,
                        3,
                        0,
                        ""
                    ],
                    [
                        63500,
                        1,
                        0,
                        ""
                    ],
                    [
                        63666.6666666667,
                        2,
                        0,
                        ""
                    ],
                    [
                        63833.3333333333,
                        1,
                        0,
                        ""
                    ]
                ],
                "bpm": 0,
                "changeBPM": null,
                "mustHitSection": true
            },
            {
                "lengthInSteps": 16,
                "sectionNotes": [
                    [
                        64333.3333333333,
                        1,
                        0,
                        ""
                    ],
                    [
                        64333.3333333333,
                        6,
                        0,
                        ""
                    ],
                    [
                        64333.3333333333,
                        0,
                        0,
                        ""
                    ],
                    [
                        64500,
                        2,
                        0,
                        ""
                    ],
                    [
                        64500,
                        5,
                        0,
                        ""
                    ],
                    [
                        64666.6666666667,
                        7,
                        583,
                        ""
                    ],
                    [
                        64833.3333333333,
                        3,
                        0,
                        ""
                    ],
                    [
                        65000,
                        1,
                        0,
                        ""
                    ]
                ],
                "bpm": 0,
                "changeBPM": null,
                "mustHitSection": true
            },
            {
                "lengthInSteps": 16,
                "sectionNotes": [
                    [
                        65333.3333333333,
                        1,
                        83,
                        ""
                    ],
                    [
                        65500,
                        5,
                        0,
                        ""
                    ],
                    [
                        65666.6666666667,
                        3,
                        0,
                        ""
                    ],
                    [
                        65666.6666666667,
                        2,
                        0,
                        ""
                    ],
                    [
                        65666.6666666667,
                        7,
                        0,
                        ""
                    ],
                    [
                        65833.3333333333,
                        1,
                        0,
                        ""
                    ],
                    [
                        66000,
                        4,
                        583,
                        ""
                    ],
                    [
                        66166.6666666667,
                        0,
                        0,
                        ""
                    ],
                    [
                        66333.3333333333,
                        1,
                        0,
                        ""
                    ]
                ],
                "bpm": 0,
                "changeBPM": null,
                "mustHitSection": true
            },
            {
                "lengthInSteps": 16,
                "sectionNotes": [
                    [
                        66666.6666666667,
                        2,
                        0,
                        ""
                    ],
                    [
                        66666.6666666667,
                        1,
                        83,
                        ""
                    ],
                    [
                        67000,
                        0,
                        0,
                        ""
                    ],
                    [
                        67000,
                        6,
                        0,
                        ""
                    ],
                    [
                        67166.6666666667,
                        3,
                        83,
                        ""
                    ],
                    [
                        67333.3333333333,
                        5,
                        0,
                        ""
                    ],
                    [
                        67500,
                        0,
                        0,
                        ""
                    ],
                    [
                        67666.6666666667,
                        3,
                        0,
                        ""
                    ],
                    [
                        67666.6666666667,
                        4,
                        0,
                        ""
                    ],
                    [
                        67833.3333333333,
                        5,
                        0,
                        ""
                    ],
                    [
                        67833.3333333333,
                        2,
                        0,
                        ""
                    ]
                ],
                "bpm": 0,
                "changeBPM": null,
                "mustHitSection": true
            },
            {
                "lengthInSteps": 16,
                "sectionNotes": [
                    [
                        68000,
                        0,
                        0,
                        ""
                    ],
                    [
                        68000,
                        3,
                        0,
                        ""
                    ],
                    [
                        68000,
                        6,
                        0,
                        ""
                    ],
                    [
                        68166.6666666667,
                        7,
                        0,
                        ""
                    ],
                    [
                        68333.3333333333,
                        4,
                        0,
                        ""
                    ],
                    [
                        68333.3333333333,
                        1,
                        0,
                        ""
                    ],
                    [
                        68500,
                        2,
                        0,
                        ""
                    ],
                    [
                        68500,
                        7,
                        0,
                        ""
                    ],
                    [
                        68666.6666666667,
                        3,
                        0,
                        ""
                    ],
                    [
                        68666.6666666667,
                        0,
                        0,
                        ""
                    ],
                    [
                        68666.6666666667,
                        6,
                        0,
                        ""
                    ],
                    [
                        69000,
                        0,
                        0,
                        ""
                    ],
                    [
                        69166.6666666667,
                        2,
                        0,
                        ""
                    ]
                ],
                "bpm": 0,
                "changeBPM": null,
                "mustHitSection": true
            },
            {
                "lengthInSteps": 16,
                "sectionNotes": [
                    [
                        69333.3333333333,
                        1,
                        83,
                        ""
                    ],
                    [
                        69333.3333333333,
                        3,
                        83,
                        ""
                    ],
                    [
                        69666.6666666667,
                        0,
                        0,
                        ""
                    ],
                    [
                        69833.3333333333,
                        1,
                        0,
                        ""
                    ],
                    [
                        70166.6666666667,
                        3,
                        0,
                        ""
                    ],
                    [
                        70333.3333333333,
                        1,
                        0,
                        ""
                    ]
                ],
                "bpm": 0,
                "changeBPM": null,
                "mustHitSection": true
            },
            {
                "lengthInSteps": 16,
                "sectionNotes": [
                    [
                        70666.6666666667,
                        2,
                        83,
                        ""
                    ],
                    [
                        70666.6666666667,
                        0,
                        83,
                        ""
                    ],
                    [
                        71000,
                        3,
                        0,
                        ""
                    ],
                    [
                        71166.6666666667,
                        2,
                        0,
                        ""
                    ],
                    [
                        71500,
                        0,
                        0,
                        ""
                    ],
                    [
                        71666.6666666667,
                        1,
                        0,
                        ""
                    ]
                ],
                "bpm": 0,
                "changeBPM": null,
                "mustHitSection": true
            },
            {
                "lengthInSteps": 16,
                "sectionNotes": [
                    [
                        72000,
                        0,
                        83,
                        ""
                    ],
                    [
                        72000,
                        3,
                        83,
                        ""
                    ],
                    [
                        72333.3333333333,
                        1,
                        0,
                        ""
                    ],
                    [
                        72500,
                        2,
                        0,
                        ""
                    ],
                    [
                        72833.3333333333,
                        2,
                        0,
                        ""
                    ],
                    [
                        73000,
                        1,
                        0,
                        ""
                    ]
                ],
                "bpm": 0,
                "changeBPM": null,
                "mustHitSection": true
            },
            {
                "lengthInSteps": 16,
                "sectionNotes": [
                    [
                        73333.3333333333,
                        1,
                        250,
                        ""
                    ],
                    [
                        73333.3333333333,
                        2,
                        0,
                        ""
                    ],
                    [
                        74000,
                        1,
                        0,
                        ""
                    ],
                    [
                        74166.6666666667,
                        1,
                        0,
                        ""
                    ],
                    [
                        74333.3333333333,
                        3,
                        0,
                        ""
                    ],
                    [
                        74500,
                        1,
                        0,
                        ""
                    ]
                ],
                "bpm": 0,
                "changeBPM": null,
                "mustHitSection": true
            },
            {
                "lengthInSteps": 16,
                "sectionNotes": [
                    [
                        74666.6666666667,
                        3,
                        0,
                        ""
                    ],
                    [
                        74666.6666666667,
                        6,
                        0,
                        ""
                    ],
                    [
                        74833.3333333333,
                        3,
                        0,
                        ""
                    ],
                    [
                        75000,
                        2,
                        0,
                        ""
                    ],
                    [
                        75000,
                        4,
                        0,
                        ""
                    ],
                    [
                        75166.6666666667,
                        1,
                        83,
                        ""
                    ],
                    [
                        75166.6666666667,
                        5,
                        0,
                        ""
                    ],
                    [
                        75333.3333333333,
                        6,
                        0,
                        ""
                    ],
                    [
                        75666.6666666667,
                        4,
                        0,
                        ""
                    ],
                    [
                        75833.3333333333,
                        7,
                        0,
                        ""
                    ]
                ],
                "bpm": 0,
                "changeBPM": null,
                "mustHitSection": true
            },
            {
                "lengthInSteps": 16,
                "sectionNotes": [
                    [
                        76000,
                        6,
                        0,
                        ""
                    ],
                    [
                        76166.6666666667,
                        7,
                        0,
                        ""
                    ],
                    [
                        76333.3333333333,
                        0,
                        0,
                        ""
                    ],
                    [
                        76333.3333333333,
                        4,
                        0,
                        ""
                    ],
                    [
                        76500,
                        0,
                        0,
                        ""
                    ],
                    [
                        76500,
                        5,
                        0,
                        ""
                    ],
                    [
                        76583.3333333333,
                        2,
                        0,
                        ""
                    ],
                    [
                        76666.6666666667,
                        3,
                        0,
                        ""
                    ],
                    [
                        76666.6666666667,
                        6,
                        0,
                        ""
                    ],
                    [
                        76833.3333333333,
                        1,
                        0,
                        ""
                    ],
                    [
                        77000,
                        6,
                        0,
                        ""
                    ],
                    [
                        77000,
                        0,
                        0,
                        ""
                    ],
                    [
                        77166.6666666667,
                        2,
                        0,
                        ""
                    ]
                ],
                "bpm": 0,
                "changeBPM": null,
                "mustHitSection": true
            },
            {
                "lengthInSteps": 16,
                "sectionNotes": [
                    [
                        77333.3333333333,
                        1,
                        0,
                        ""
                    ],
                    [
                        77500,
                        3,
                        0,
                        ""
                    ],
                    [
                        77666.6666666667,
                        1,
                        0,
                        ""
                    ],
                    [
                        77833.3333333333,
                        2,
                        0,
                        ""
                    ],
                    [
                        78250,
                        3,
                        0,
                        ""
                    ],
                    [
                        78416.6666666667,
                        1,
                        0,
                        ""
                    ]
                ],
                "bpm": 0,
                "changeBPM": null,
                "mustHitSection": true
            },
            {
                "lengthInSteps": 16,
                "sectionNotes": [
                    [
                        78666.6666666667,
                        0,
                        0,
                        ""
                    ],
                    [
                        78833.3333333333,
                        1,
                        0,
                        ""
                    ],
                    [
                        79000,
                        2,
                        167,
                        ""
                    ],
                    [
                        79333.3333333333,
                        2,
                        83,
                        ""
                    ],
                    [
                        79500,
                        3,
                        0,
                        ""
                    ],
                    [
                        79666.6666666667,
                        2,
                        0,
                        ""
                    ],
                    [
                        79833.3333333333,
                        0,
                        0,
                        ""
                    ]
                ],
                "bpm": 0,
                "changeBPM": null,
                "mustHitSection": true
            },
            {
                "lengthInSteps": 16,
                "sectionNotes": [
                    [
                        80000,
                        3,
                        0,
                        ""
                    ],
                    [
                        80000,
                        5,
                        0,
                        ""
                    ],
                    [
                        80166.6666666667,
                        3,
                        0,
                        ""
                    ],
                    [
                        80333.3333333333,
                        2,
                        0,
                        ""
                    ],
                    [
                        80333.3333333333,
                        4,
                        0,
                        ""
                    ],
                    [
                        80500,
                        1,
                        83,
                        ""
                    ],
                    [
                        80500,
                        7,
                        0,
                        ""
                    ],
                    [
                        80666.6666666667,
                        5,
                        0,
                        ""
                    ],
                    [
                        81000,
                        6,
                        0,
                        ""
                    ]
                ],
                "bpm": 0,
                "changeBPM": null,
                "mustHitSection": true
            },
            {
                "lengthInSteps": 16,
                "sectionNotes": [
                    [
                        81333.3333333333,
                        5,
                        0,
                        ""
                    ],
                    [
                        81666.6666666667,
                        2,
                        0,
                        ""
                    ],
                    [
                        81666.6666666667,
                        5,
                        0,
                        ""
                    ],
                    [
                        81833.3333333333,
                        0,
                        0,
                        ""
                    ],
                    [
                        81916.6666666667,
                        2,
                        0,
                        ""
                    ],
                    [
                        82000,
                        3,
                        0,
                        ""
                    ],
                    [
                        82000,
                        5,
                        0,
                        ""
                    ],
                    [
                        82166.6666666667,
                        1,
                        0,
                        ""
                    ],
                    [
                        82333.3333333333,
                        1,
                        0,
                        ""
                    ],
                    [
                        82500,
                        3,
                        0,
                        ""
                    ]
                ],
                "bpm": 0,
                "changeBPM": null,
                "mustHitSection": true
            },
            {
                "lengthInSteps": 16,
                "sectionNotes": [
                    [
                        82666.6666666667,
                        2,
                        0,
                        ""
                    ],
                    [
                        82833.3333333333,
                        3,
                        0,
                        ""
                    ],
                    [
                        83166.6666666667,
                        1,
                        0,
                        ""
                    ],
                    [
                        83333.3333333333,
                        3,
                        0,
                        ""
                    ],
                    [
                        83666.6666666667,
                        0,
                        0,
                        ""
                    ],
                    [
                        83833.3333333333,
                        1,
                        83,
                        ""
                    ]
                ],
                "bpm": 0,
                "changeBPM": null,
                "mustHitSection": true
            },
            {
                "lengthInSteps": 16,
                "sectionNotes": [
                    [
                        84166.6666666667,
                        2,
                        0,
                        ""
                    ],
                    [
                        84333.3333333333,
                        3,
                        0,
                        ""
                    ],
                    [
                        84500,
                        0,
                        0,
                        ""
                    ],
                    [
                        84666.6666666667,
                        1,
                        0,
                        ""
                    ],
                    [
                        84833.3333333333,
                        2,
                        0,
                        ""
                    ],
                    [
                        85000,
                        0,
                        0,
                        ""
                    ],
                    [
                        85166.6666666667,
                        3,
                        0,
                        ""
                    ],
                    [
                        85250,
                        0,
                        0,
                        ""
                    ]
                ],
                "bpm": 0,
                "changeBPM": null,
                "mustHitSection": true
            },
            {
                "lengthInSteps": 16,
                "sectionNotes": [
                    [
                        85333.3333333333,
                        1,
                        83,
                        ""
                    ]
                ],
                "bpm": 0,
                "changeBPM": null,
                "mustHitSection": true
            }
        ]
    }
}