{
	"song": {
		"speed": 2,
		"stage": "PhillyStreets",
		"player1": "PicoWeekend",
		"player2": "Darnell",
		"notes": [
			{
				"lengthInSteps": 16,
				"sectionNotes": [
					[
						0,
						0,
						290,
						""
					],
					[
						387,
						1,
						0,
						""
					],
					[
						774.193548387097,
						2,
						0,
						""
					],
					[
						967,
						3,
						0,
						""
					],
					[
						1161.29032258065,
						0,
						0,
						""
					],
					[
						1354,
						1,
						0,
						""
					]
				],
				"bpm": 0,
				"changeBPM": null,
				"mustHitSection": false
			},
			{
				"lengthInSteps": 16,
				"sectionNotes": [
					[
						1548.38709677419,
						3,
						0,
						""
					],
					[
						1935,
						3,
						0,
						""
					],
					[
						2322,
						3,
						0,
						""
					],
					[
						2709.67741935484,
						1,
						0,
						""
					],
					[
						2903.22580645161,
						0,
						0,
						""
					]
				],
				"bpm": 0,
				"changeBPM": null,
				"mustHitSection": false
			},
			{
				"lengthInSteps": 16,
				"sectionNotes": [
					[
						3096.77419354839,
						0,
						290.322580645161,
						""
					],
					[
						3483,
						1,
						0,
						""
					],
					[
						3870.96774193548,
						2,
						0,
						""
					],
					[
						4064,
						3,
						0,
						""
					],
					[
						4258.06451612903,
						0,
						0,
						""
					],
					[
						4451,
						1,
						0,
						""
					]
				],
				"bpm": 0,
				"changeBPM": null,
				"mustHitSection": true
			},
			{
				"lengthInSteps": 16,
				"sectionNotes": [
					[
						4645.16129032258,
						3,
						0,
						""
					],
					[
						5032,
						3,
						0,
						""
					],
					[
						5419.35483870968,
						1,
						0,
						""
					],
					[
						5612.90322580645,
						0,
						0,
						""
					],
					[
						5806.45161290323,
						3,
						0,
						""
					]
				],
				"bpm": 0,
				"changeBPM": null,
				"mustHitSection": true
			},
			{
				"lengthInSteps": 16,
				"sectionNotes": [
					[
						6193.54838709677,
						2,
						290.322580645161,
						""
					],
					[
						6580,
						1,
						0,
						""
					],
					[
						6967.74193548387,
						2,
						0,
						""
					],
					[
						7161,
						3,
						0,
						""
					],
					[
						7354.83870967742,
						0,
						0,
						""
					],
					[
						7548,
						1,
						0,
						""
					]
				],
				"bpm": 0,
				"changeBPM": null,
				"mustHitSection": false
			},
			{
				"lengthInSteps": 16,
				"sectionNotes": [
					[
						7741.93548387097,
						0,
						0,
						""
					],
					[
						7935,
						1,
						0,
						""
					],
					[
						8129,
						3,
						0,
						""
					],
					[
						8322,
						1,
						0,
						""
					],
					[
						8516.12903225806,
						0,
						0,
						""
					],
					[
						8903,
						3,
						0,
						""
					],
					[
						9096,
						3,
						0,
						""
					]
				],
				"bpm": 0,
				"changeBPM": null,
				"mustHitSection": false
			},
			{
				"lengthInSteps": 16,
				"sectionNotes": [
					[
						9290.32258064516,
						2,
						290.322580645161,
						""
					],
					[
						9677,
						3,
						0,
						""
					],
					[
						10064.5161290323,
						2,
						0,
						""
					],
					[
						10258.064516129,
						3,
						0,
						""
					],
					[
						10451,
						0,
						0,
						""
					],
					[
						10645,
						1,
						0,
						""
					]
				],
				"bpm": 0,
				"changeBPM": null,
				"mustHitSection": true
			},
			{
				"lengthInSteps": 16,
				"sectionNotes": [
					[
						10838.7096774194,
						0,
						0,
						""
					],
					[
						11225,
						3,
						0,
						""
					],
					[
						11419,
						1,
						0,
						""
					],
					[
						11612,
						3,
						0,
						""
					],
					[
						11806.4516129032,
						2,
						0,
						""
					],
					[
						12000,
						3,
						0,
						""
					],
					[
						12193.5483870968,
						0,
						0,
						""
					]
				],
				"bpm": 0,
				"changeBPM": null,
				"mustHitSection": true
			},
			{
				"lengthInSteps": 16,
				"sectionNotes": [
					[
						12387.0967741935,
						0,
						0,
						""
					],
					[
						12580,
						1,
						0,
						""
					],
					[
						12774.1935483871,
						3,
						0,
						""
					],
					[
						12967,
						1,
						0,
						""
					],
					[
						13161.2903225806,
						2,
						0,
						""
					],
					[
						13548,
						0,
						0,
						""
					],
					[
						13741.935483871,
						1,
						0,
						""
					]
				],
				"bpm": 0,
				"changeBPM": null,
				"mustHitSection": false
			},
			{
				"lengthInSteps": 16,
				"sectionNotes": [
					[
						13935.4838709677,
						3,
						0,
						""
					],
					[
						14129.0322580645,
						2,
						0,
						""
					],
					[
						14322.5806451613,
						0,
						0,
						""
					],
					[
						14516.1290322581,
						2,
						0,
						""
					],
					[
						14709.6774193548,
						1,
						0,
						""
					],
					[
						15096,
						0,
						0,
						""
					],
					[
						15290,
						3,
						0,
						""
					]
				],
				"bpm": 0,
				"changeBPM": null,
				"mustHitSection": false
			},
			{
				"lengthInSteps": 16,
				"sectionNotes": [
					[
						15483.8709677419,
						2,
						0,
						""
					],
					[
						15677,
						1,
						0,
						""
					],
					[
						15870.9677419355,
						3,
						0,
						""
					],
					[
						16064,
						1,
						0,
						""
					],
					[
						16258,
						3,
						0,
						""
					],
					[
						16451,
						0,
						0,
						""
					],
					[
						16645,
						2,
						0,
						""
					],
					[
						16838,
						3,
						0,
						""
					]
				],
				"bpm": 0,
				"changeBPM": null,
				"mustHitSection": false
			},
			{
				"lengthInSteps": 16,
				"sectionNotes": [
					[
						17032.2580645161,
						1,
						0,
						""
					],
					[
						17225.8064516129,
						2,
						0,
						""
					],
					[
						17419.3548387097,
						0,
						0,
						""
					],
					[
						17612.9032258065,
						3,
						0,
						""
					],
					[
						17806.4516129032,
						0,
						0,
						""
					],
					[
						18000,
						3,
						0,
						""
					],
					[
						18193,
						2,
						0,
						""
					],
					[
						18387,
						3,
						0,
						""
					]
				],
				"bpm": 0,
				"changeBPM": null,
				"mustHitSection": false
			},
			{
				"lengthInSteps": 16,
				"sectionNotes": [
					[
						18580.6451612903,
						0,
						0,
						""
					],
					[
						18774,
						1,
						0,
						""
					],
					[
						18967.7419354839,
						3,
						0,
						""
					],
					[
						19161,
						1,
						0,
						""
					],
					[
						19354.8387096774,
						2,
						0,
						""
					],
					[
						19741,
						0,
						0,
						""
					],
					[
						19935,
						3,
						0,
						""
					]
				],
				"bpm": 0,
				"changeBPM": null,
				"mustHitSection": true
			},
			{
				"lengthInSteps": 16,
				"sectionNotes": [
					[
						20129.0322580645,
						0,
						0,
						""
					],
					[
						20322.5806451613,
						2,
						0,
						""
					],
					[
						20516.1290322581,
						1,
						0,
						""
					],
					[
						20709.6774193548,
						0,
						0,
						""
					],
					[
						20903.2258064516,
						3,
						193.548387096774,
						""
					],
					[
						21290,
						0,
						0,
						""
					],
					[
						21483,
						3,
						0,
						""
					]
				],
				"bpm": 0,
				"changeBPM": null,
				"mustHitSection": true
			},
			{
				"lengthInSteps": 16,
				"sectionNotes": [
					[
						21677.4193548387,
						2,
						0,
						""
					],
					[
						21870,
						1,
						0,
						""
					],
					[
						22064.5161290323,
						2,
						0,
						""
					],
					[
						22258.064516129,
						0,
						0,
						""
					],
					[
						22451,
						3,
						0,
						""
					],
					[
						22645,
						0,
						0,
						""
					],
					[
						22838,
						2,
						0,
						""
					],
					[
						23032,
						3,
						0,
						""
					]
				],
				"bpm": 0,
				"changeBPM": null,
				"mustHitSection": true
			},
			{
				"lengthInSteps": 16,
				"sectionNotes": [
					[
						23225.8064516129,
						0,
						0,
						""
					],
					[
						23419.3548387097,
						0,
						0,
						""
					],
					[
						23612.9032258065,
						2,
						0,
						""
					],
					[
						23806.4516129032,
						1,
						96.7741935483871,
						""
					],
					[
						24000,
						3,
						0,
						""
					],
					[
						24193,
						3,
						0,
						""
					],
					[
						24387,
						2,
						0,
						""
					],
					[
						24580,
						3,
						0,
						""
					]
				],
				"bpm": 0,
				"changeBPM": null,
				"mustHitSection": true
			},
			{
				"lengthInSteps": 16,
				"sectionNotes": [
					[
						24774.1935483871,
						0,
						0,
						""
					],
					[
						24967.7419354839,
						2,
						0,
						""
					],
					[
						25161.2903225806,
						1,
						0,
						""
					],
					[
						25354.8387096774,
						2,
						0,
						""
					],
					[
						25548.3870967742,
						3,
						0,
						""
					],
					[
						25741,
						0,
						0,
						""
					],
					[
						25935.4838709677,
						3,
						0,
						""
					],
					[
						26129,
						0,
						0,
						""
					]
				],
				"bpm": 0,
				"changeBPM": null,
				"mustHitSection": false
			},
			{
				"lengthInSteps": 16,
				"sectionNotes": [
					[
						26322.5806451613,
						2,
						0,
						""
					],
					[
						26516,
						0,
						0,
						""
					],
					[
						26709.6774193548,
						1,
						0,
						""
					],
					[
						26903,
						0,
						0,
						""
					],
					[
						27096,
						2,
						96,
						""
					],
					[
						27290,
						0,
						0,
						""
					],
					[
						27483,
						2,
						0,
						""
					],
					[
						27677.4193548387,
						1,
						0,
						""
					]
				],
				"bpm": 0,
				"changeBPM": null,
				"mustHitSection": false
			},
			{
				"lengthInSteps": 16,
				"sectionNotes": [
					[
						27870.9677419355,
						3,
						0,
						""
					],
					[
						28258,
						3,
						0,
						""
					],
					[
						28451.6129032258,
						2,
						0,
						""
					],
					[
						28645,
						3,
						0,
						""
					],
					[
						28838,
						0,
						0,
						""
					],
					[
						29032.2580645161,
						3,
						0,
						""
					],
					[
						29225,
						1,
						0,
						""
					]
				],
				"bpm": 0,
				"changeBPM": null,
				"mustHitSection": false
			},
			{
				"lengthInSteps": 16,
				"sectionNotes": [
					[
						29419.3548387097,
						0,
						0,
						""
					],
					[
						29612,
						1,
						0,
						""
					],
					[
						29806,
						3,
						0,
						""
					],
					[
						30000,
						2,
						0,
						""
					],
					[
						30193,
						3,
						0,
						""
					],
					[
						30387,
						1,
						96,
						""
					],
					[
						30580.6451612903,
						0,
						0,
						""
					],
					[
						30774.1935483871,
						2,
						0,
						""
					]
				],
				"bpm": 0,
				"changeBPM": null,
				"mustHitSection": false
			},
			{
				"lengthInSteps": 16,
				"sectionNotes": [
					[
						30967.7419354839,
						0,
						0,
						""
					],
					[
						31161,
						1,
						0,
						""
					],
					[
						31354.8387096774,
						3,
						0,
						""
					],
					[
						31548.3870967742,
						0,
						0,
						""
					],
					[
						31741,
						2,
						0,
						""
					],
					[
						31935,
						0,
						290,
						""
					],
					[
						32322.5806451613,
						2,
						0,
						""
					]
				],
				"bpm": 0,
				"changeBPM": null,
				"mustHitSection": true
			},
			{
				"lengthInSteps": 16,
				"sectionNotes": [
					[
						32516.1290322581,
						1,
						0,
						""
					],
					[
						32709.6774193548,
						3,
						0,
						""
					],
					[
						32903.2258064516,
						2,
						0,
						""
					],
					[
						33096,
						0,
						0,
						""
					],
					[
						33290.3225806452,
						1,
						96.7741935483871,
						""
					],
					[
						33483.8709677419,
						3,
						290.322580645156,
						""
					],
					[
						33870.9677419355,
						0,
						0,
						""
					]
				],
				"bpm": 0,
				"changeBPM": null,
				"mustHitSection": true
			},
			{
				"lengthInSteps": 16,
				"sectionNotes": [
					[
						34064.5161290323,
						3,
						290.322580645159,
						""
					],
					[
						34451.6129032258,
						0,
						0,
						""
					],
					[
						34645.1612903226,
						0,
						0,
						""
					],
					[
						34838,
						2,
						0,
						""
					],
					[
						35032.2580645161,
						1,
						0,
						""
					],
					[
						35225.8064516129,
						2,
						0,
						""
					],
					[
						35419.3548387097,
						0,
						0,
						""
					]
				],
				"bpm": 0,
				"changeBPM": null,
				"mustHitSection": true
			},
			{
				"lengthInSteps": 16,
				"sectionNotes": [
					[
						35612.9032258065,
						1,
						0,
						""
					],
					[
						35806.4516129032,
						0,
						0,
						""
					],
					[
						36000,
						2,
						0,
						""
					],
					[
						36193.5483870968,
						3,
						0,
						""
					],
					[
						36387.0967741935,
						0,
						0,
						""
					],
					[
						36580.6451612903,
						0,
						0,
						""
					],
					[
						36774.1935483871,
						1,
						0,
						""
					],
					[
						36967.7419354839,
						1,
						193.548387096769,
						""
					]
				],
				"bpm": 0,
				"changeBPM": null,
				"mustHitSection": true
			},
			{
				"lengthInSteps": 16,
				"sectionNotes": [
					[
						37161.2903225807,
						0,
						193.548387096773,
						""
					],
					[
						37548,
						3,
						0,
						""
					],
					[
						37741.935483871,
						1,
						0,
						""
					],
					[
						37935.4838709677,
						0,
						0,
						""
					],
					[
						38129.0322580645,
						2,
						0,
						""
					],
					[
						38322,
						1,
						0,
						""
					],
					[
						38516,
						3,
						0,
						""
					]
				],
				"bpm": 0,
				"changeBPM": null,
				"mustHitSection": false
			},
			{
				"lengthInSteps": 16,
				"sectionNotes": [
					[
						39870.9677419355,
						0,
						96.7741935483864,
						""
					],
					[
						38709.6774193548,
						0,
						0,
						""
					],
					[
						38903.2258064516,
						1,
						0,
						""
					],
					[
						39096.7741935484,
						0,
						0,
						""
					],
					[
						39290.3225806452,
						2,
						0,
						""
					],
					[
						39483.8709677419,
						3,
						0,
						""
					],
					[
						39677.4193548387,
						2,
						0,
						""
					],
					[
						40064.5161290323,
						3,
						0,
						""
					]
				],
				"bpm": 0,
				"changeBPM": null,
				"mustHitSection": false
			},
			{
				"lengthInSteps": 16,
				"sectionNotes": [
					[
						40258.064516129,
						0,
						0,
						""
					],
					[
						40645,
						0,
						0,
						""
					],
					[
						40838.7096774193,
						2,
						0,
						""
					],
					[
						41032.2580645161,
						0,
						0,
						""
					],
					[
						41225,
						2,
						0,
						""
					],
					[
						41419.3548387097,
						3,
						0,
						""
					],
					[
						41612,
						1,
						0,
						""
					]
				],
				"bpm": 0,
				"changeBPM": null,
				"mustHitSection": false
			},
			{
				"lengthInSteps": 16,
				"sectionNotes": [
					[
						41806.4516129032,
						2,
						0,
						""
					],
					[
						42000,
						1,
						0,
						""
					],
					[
						42193,
						0,
						0,
						""
					],
					[
						42387.0967741935,
						3,
						0,
						""
					],
					[
						42580,
						0,
						0,
						""
					],
					[
						42774,
						1,
						96,
						""
					],
					[
						42967,
						2,
						96,
						""
					]
				],
				"bpm": 0,
				"changeBPM": null,
				"mustHitSection": false
			},
			{
				"lengthInSteps": 16,
				"sectionNotes": [
					[
						43354.8387096774,
						0,
						0,
						""
					],
					[
						43548,
						0,
						0,
						""
					],
					[
						43741,
						3,
						0,
						""
					],
					[
						43935.4838709677,
						1,
						0,
						""
					],
					[
						44129.0322580645,
						2,
						0,
						""
					],
					[
						44322,
						0,
						0,
						""
					],
					[
						44516,
						1,
						0,
						""
					],
					[
						44709,
						3,
						0,
						""
					]
				],
				"bpm": 0,
				"changeBPM": null,
				"mustHitSection": true
			},
			{
				"lengthInSteps": 16,
				"sectionNotes": [
					[
						44903.2258064516,
						3,
						0,
						""
					],
					[
						45096.7741935484,
						3,
						0,
						""
					],
					[
						45290.3225806452,
						2,
						0,
						""
					],
					[
						45483.8709677419,
						0,
						0,
						""
					],
					[
						45677.4193548387,
						1,
						0,
						""
					],
					[
						45870,
						3,
						0,
						""
					],
					[
						46064.5161290323,
						0,
						0,
						""
					],
					[
						46258,
						1,
						0,
						""
					]
				],
				"bpm": 0,
				"changeBPM": null,
				"mustHitSection": true
			},
			{
				"lengthInSteps": 16,
				"sectionNotes": [
					[
						46451.6129032258,
						1,
						0,
						""
					],
					[
						46838,
						0,
						0,
						""
					],
					[
						47032.2580645161,
						3,
						0,
						""
					],
					[
						47225.8064516129,
						2,
						0,
						""
					],
					[
						47419.3548387097,
						0,
						0,
						""
					],
					[
						47612.9032258064,
						1,
						0,
						""
					],
					[
						47806.4516129032,
						3,
						0,
						""
					]
				],
				"bpm": 0,
				"changeBPM": null,
				"mustHitSection": true
			},
			{
				"lengthInSteps": 16,
				"sectionNotes": [
					[
						48000,
						2,
						0,
						""
					],
					[
						48193.5483870968,
						3,
						0,
						""
					],
					[
						48387,
						0,
						0,
						""
					],
					[
						48580.6451612903,
						3,
						0,
						""
					],
					[
						48774,
						1,
						0,
						""
					],
					[
						48967.7419354839,
						3,
						0,
						""
					],
					[
						49161,
						2,
						0,
						""
					],
					[
						49354.8387096774,
						2,
						193.548387096774,
						""
					]
				],
				"bpm": 0,
				"changeBPM": null,
				"mustHitSection": true
			},
			{
				"lengthInSteps": 16,
				"sectionNotes": [
					[
						49548.3870967742,
						2,
						0,
						""
					],
					[
						49741,
						1,
						0,
						""
					],
					[
						49935,
						3,
						0,
						""
					],
					[
						50129,
						1,
						0,
						""
					],
					[
						50322,
						2,
						0,
						""
					],
					[
						50516,
						0,
						0,
						""
					],
					[
						50709,
						1,
						96,
						""
					],
					[
						50903,
						3,
						0,
						""
					]
				],
				"bpm": 0,
				"changeBPM": null,
				"mustHitSection": false
			},
			{
				"lengthInSteps": 16,
				"sectionNotes": [
					[
						51096.7741935484,
						2,
						0,
						""
					],
					[
						51290,
						0,
						0,
						""
					],
					[
						51483,
						2,
						0,
						""
					],
					[
						51677,
						0,
						0,
						""
					],
					[
						51870,
						1,
						0,
						""
					],
					[
						52258,
						1,
						0,
						""
					],
					[
						52451,
						1,
						0,
						""
					]
				],
				"bpm": 0,
				"changeBPM": null,
				"mustHitSection": false
			},
			{
				"lengthInSteps": 16,
				"sectionNotes": [
					[
						52645.1612903226,
						2,
						0,
						""
					],
					[
						52838,
						1,
						0,
						""
					],
					[
						53032,
						3,
						0,
						""
					],
					[
						53225,
						1,
						0,
						""
					],
					[
						53419,
						1,
						0,
						""
					],
					[
						53612,
						0,
						0,
						""
					],
					[
						53806.4516129032,
						1,
						96.7741935483871,
						""
					],
					[
						54000,
						3,
						0,
						""
					]
				],
				"bpm": 0,
				"changeBPM": null,
				"mustHitSection": true
			},
			{
				"lengthInSteps": 16,
				"sectionNotes": [
					[
						54193.5483870968,
						2,
						0,
						""
					],
					[
						54387,
						0,
						0,
						""
					],
					[
						54580.6451612903,
						2,
						0,
						""
					],
					[
						54774,
						0,
						0,
						""
					],
					[
						54967.7419354839,
						1,
						193.548387096774,
						""
					],
					[
						55354.8387096774,
						3,
						0,
						""
					],
					[
						55548,
						1,
						0,
						""
					]
				],
				"bpm": 0,
				"changeBPM": null,
				"mustHitSection": true
			},
			{
				"lengthInSteps": 16,
				"sectionNotes": [
					[
						55741.935483871,
						2,
						290.322580645159,
						""
					],
					[
						56129,
						1,
						0,
						""
					],
					[
						56516.1290322581,
						2,
						0,
						""
					],
					[
						56709.6774193548,
						3,
						0,
						""
					],
					[
						56903.2258064516,
						0,
						0,
						""
					],
					[
						57096.7741935484,
						1,
						0,
						""
					]
				],
				"bpm": 0,
				"changeBPM": null,
				"mustHitSection": false
			},
			{
				"lengthInSteps": 16,
				"sectionNotes": [
					[
						57290.3225806452,
						2,
						0,
						""
					],
					[
						57483.8709677419,
						0,
						0,
						""
					],
					[
						57677.4193548387,
						2,
						0,
						""
					],
					[
						57870.9677419355,
						0,
						0,
						""
					],
					[
						58064,
						3,
						0,
						""
					],
					[
						58451.6129032258,
						2,
						0,
						""
					],
					[
						58645,
						3,
						0,
						""
					]
				],
				"bpm": 0,
				"changeBPM": null,
				"mustHitSection": false
			},
			{
				"lengthInSteps": 16,
				"sectionNotes": [
					[
						58838.7096774194,
						2,
						290.322580645159,
						""
					],
					[
						59225,
						3,
						193,
						""
					],
					[
						59612,
						2,
						96,
						""
					],
					[
						59806.4516129032,
						0,
						0,
						""
					],
					[
						60000,
						1,
						0,
						""
					],
					[
						60193,
						0,
						0,
						""
					]
				],
				"bpm": 0,
				"changeBPM": null,
				"mustHitSection": true
			},
			{
				"lengthInSteps": 16,
				"sectionNotes": [
					[
						60387.0967741936,
						1,
						0,
						""
					],
					[
						60580,
						3,
						0,
						""
					],
					[
						60774,
						1,
						0,
						""
					],
					[
						60967,
						3,
						0,
						""
					],
					[
						61161,
						2,
						193,
						""
					],
					[
						61548,
						1,
						0,
						""
					],
					[
						61741,
						1,
						0,
						""
					]
				],
				"bpm": 0,
				"changeBPM": null,
				"mustHitSection": true
			},
			{
				"lengthInSteps": 16,
				"sectionNotes": [
					[
						61935.4838709678,
						1,
						0,
						""
					],
					[
						62128.8064516129,
						0,
						0,
						""
					],
					[
						62225.5806451613,
						2,
						0,
						""
					],
					[
						62322.5806451613,
						3,
						0,
						""
					],
					[
						62515.9032258064,
						0,
						0,
						""
					],
					[
						62709,
						1,
						0,
						""
					],
					[
						62903,
						0,
						0,
						""
					],
					[
						62999.7741935484,
						1,
						0,
						""
					],
					[
						63096.7741935484,
						3,
						0,
						""
					],
					[
						63290.0967741935,
						0,
						0,
						""
					]
				],
				"bpm": 0,
				"changeBPM": null,
				"mustHitSection": false
			},
			{
				"lengthInSteps": 16,
				"sectionNotes": [
					[
						63483.870967742,
						1,
						0,
						""
					],
					[
						63677.1935483871,
						3,
						0,
						""
					],
					[
						63773.9677419355,
						0,
						0,
						""
					],
					[
						63870.7419354839,
						2,
						0,
						""
					],
					[
						64064.2903225806,
						0,
						0,
						""
					],
					[
						64257.8387096774,
						3,
						0,
						""
					],
					[
						64451.3870967742,
						0,
						0,
						""
					],
					[
						64548.1612903226,
						1,
						0,
						""
					],
					[
						64645.1612903226,
						2,
						0,
						""
					],
					[
						64838.4838709677,
						0,
						0,
						""
					],
					[
						64935.2580645161,
						3,
						0,
						""
					]
				],
				"bpm": 0,
				"changeBPM": null,
				"mustHitSection": false
			},
			{
				"lengthInSteps": 16,
				"sectionNotes": [
					[
						65032.2580645162,
						1,
						0,
						""
					],
					[
						65225.8064516129,
						0,
						0,
						""
					],
					[
						65322.5806451613,
						2,
						0,
						""
					],
					[
						65419.3548387097,
						3,
						0,
						""
					],
					[
						65612.9032258064,
						0,
						0,
						""
					],
					[
						65806,
						1,
						0,
						""
					],
					[
						66000,
						0,
						0,
						""
					],
					[
						66096.7741935484,
						1,
						0,
						""
					],
					[
						66193.5483870968,
						3,
						0,
						""
					],
					[
						66387.0967741935,
						0,
						0,
						""
					]
				],
				"bpm": 0,
				"changeBPM": null,
				"mustHitSection": true
			},
			{
				"lengthInSteps": 16,
				"sectionNotes": [
					[
						66580.6451612904,
						1,
						0,
						""
					],
					[
						66774.1935483871,
						3,
						0,
						""
					],
					[
						66870.9677419355,
						0,
						0,
						""
					],
					[
						66967.7419354839,
						2,
						0,
						""
					],
					[
						67161.2903225806,
						0,
						0,
						""
					],
					[
						67354.8387096774,
						3,
						0,
						""
					],
					[
						67548.3870967742,
						0,
						0,
						""
					],
					[
						67645.1612903226,
						1,
						0,
						""
					],
					[
						67741.935483871,
						2,
						0,
						""
					],
					[
						67935.4838709677,
						0,
						0,
						""
					],
					[
						68032.2580645161,
						3,
						0,
						""
					]
				],
				"bpm": 0,
				"changeBPM": null,
				"mustHitSection": true
			},
			{
				"lengthInSteps": 16,
				"sectionNotes": [
					[
						68129.0322580646,
						1,
						0,
						""
					],
					[
						68322.8064516129,
						0,
						0,
						""
					],
					[
						68419.5806451613,
						2,
						0,
						""
					],
					[
						68516.1290322581,
						3,
						0,
						""
					],
					[
						68709.9032258064,
						0,
						0,
						""
					],
					[
						68903,
						1,
						0,
						""
					],
					[
						69097,
						0,
						0,
						""
					],
					[
						69193.7741935484,
						1,
						0,
						""
					],
					[
						69290.3225806452,
						3,
						0,
						""
					],
					[
						69484.0967741935,
						0,
						0,
						""
					]
				],
				"bpm": 0,
				"changeBPM": null,
				"mustHitSection": false
			},
			{
				"lengthInSteps": 16,
				"sectionNotes": [
					[
						69677.4193548388,
						1,
						0,
						""
					],
					[
						69871.1935483871,
						3,
						0,
						""
					],
					[
						69967.9677419355,
						0,
						0,
						""
					],
					[
						70064.7419354839,
						2,
						0,
						""
					],
					[
						70258.2903225806,
						0,
						0,
						""
					],
					[
						70451.8387096774,
						3,
						0,
						""
					],
					[
						70645.3870967742,
						0,
						0,
						""
					],
					[
						70742.1612903226,
						1,
						0,
						""
					],
					[
						70838.7096774193,
						2,
						0,
						""
					],
					[
						71032.4838709677,
						0,
						0,
						""
					],
					[
						71129.2580645161,
						3,
						0,
						""
					]
				],
				"bpm": 0,
				"changeBPM": null,
				"mustHitSection": false
			},
			{
				"lengthInSteps": 16,
				"sectionNotes": [
					[
						71225.806451613,
						1,
						0,
						""
					],
					[
						71418.8064516129,
						0,
						0,
						""
					],
					[
						71515.5806451613,
						2,
						0,
						""
					],
					[
						71612.9032258064,
						3,
						0,
						""
					],
					[
						71805.9032258064,
						0,
						0,
						""
					],
					[
						71999,
						1,
						0,
						""
					],
					[
						72193,
						0,
						0,
						""
					],
					[
						72289.7741935484,
						1,
						0,
						""
					],
					[
						72387.0967741935,
						3,
						0,
						""
					],
					[
						72580.0967741935,
						0,
						0,
						""
					]
				],
				"bpm": 0,
				"changeBPM": null,
				"mustHitSection": true
			},
			{
				"lengthInSteps": 16,
				"sectionNotes": [
					[
						72774.1935483872,
						1,
						0,
						""
					],
					[
						72967.1935483871,
						3,
						0,
						""
					],
					[
						73063.9677419355,
						0,
						0,
						""
					],
					[
						73160.7419354839,
						2,
						0,
						""
					],
					[
						73354.2903225806,
						0,
						0,
						""
					],
					[
						73547.8387096774,
						3,
						0,
						""
					],
					[
						73741.3870967742,
						0,
						0,
						""
					],
					[
						73838.1612903226,
						1,
						0,
						""
					],
					[
						73935.4838709677,
						2,
						0,
						""
					],
					[
						74128.4838709677,
						0,
						0,
						""
					],
					[
						74225.2580645161,
						3,
						0,
						""
					]
				],
				"bpm": 0,
				"changeBPM": null,
				"mustHitSection": true
			},
			{
				"lengthInSteps": 16,
				"sectionNotes": [
					[
						74322.9677419355,
						0,
						0,
						""
					],
					[
						74516.7096774194,
						2,
						0,
						""
					],
					[
						74710.2580645161,
						1,
						0,
						""
					],
					[
						74903.8064516129,
						2,
						0,
						""
					],
					[
						75097.3548387097,
						3,
						0,
						""
					],
					[
						75289.9677419355,
						0,
						0,
						""
					],
					[
						75484.4516129032,
						3,
						0,
						""
					],
					[
						75677.9677419355,
						0,
						0,
						""
					]
				],
				"bpm": 0,
				"changeBPM": null,
				"mustHitSection": false
			},
			{
				"lengthInSteps": 16,
				"sectionNotes": [
					[
						75870.9677419356,
						2,
						0,
						""
					],
					[
						76064.9677419355,
						0,
						0,
						""
					],
					[
						76258.6451612903,
						1,
						0,
						""
					],
					[
						76451.9677419355,
						0,
						0,
						""
					],
					[
						76644.9677419355,
						2,
						96,
						""
					],
					[
						76838.9677419355,
						0,
						0,
						""
					],
					[
						77031.9677419355,
						2,
						0,
						""
					],
					[
						77226.3870967742,
						1,
						0,
						""
					]
				],
				"bpm": 0,
				"changeBPM": null,
				"mustHitSection": false
			},
			{
				"lengthInSteps": 16,
				"sectionNotes": [
					[
						77419.3548387098,
						3,
						0,
						""
					],
					[
						77806.9677419355,
						3,
						0,
						""
					],
					[
						78000.5806451613,
						2,
						0,
						""
					],
					[
						78193.9677419355,
						3,
						0,
						""
					],
					[
						78386.9677419355,
						0,
						0,
						""
					],
					[
						78580.6451612903,
						3,
						0,
						""
					],
					[
						78773.9677419355,
						1,
						0,
						""
					]
				],
				"bpm": 0,
				"changeBPM": null,
				"mustHitSection": false
			},
			{
				"lengthInSteps": 16,
				"sectionNotes": [
					[
						78967.9677419355,
						0,
						0,
						""
					],
					[
						79160.9677419355,
						1,
						0,
						""
					],
					[
						79354.9677419355,
						3,
						0,
						""
					],
					[
						79548.9677419355,
						2,
						0,
						""
					],
					[
						79741.9677419355,
						3,
						0,
						""
					],
					[
						79935.9677419355,
						1,
						96,
						""
					],
					[
						80129.6129032258,
						0,
						0,
						""
					],
					[
						80323.1612903226,
						2,
						0,
						""
					]
				],
				"bpm": 0,
				"changeBPM": null,
				"mustHitSection": false
			},
			{
				"lengthInSteps": 16,
				"sectionNotes": [
					[
						80516.1290322582,
						0,
						0,
						""
					],
					[
						80709.9677419355,
						1,
						0,
						""
					],
					[
						80903.8064516129,
						3,
						0,
						""
					],
					[
						81097.3548387097,
						0,
						0,
						""
					],
					[
						81289.9677419355,
						2,
						0,
						""
					],
					[
						81483.9677419355,
						0,
						290,
						""
					],
					[
						81871.5483870968,
						2,
						0,
						""
					]
				],
				"bpm": 0,
				"changeBPM": null,
				"mustHitSection": true
			},
			{
				"lengthInSteps": 16,
				"sectionNotes": [
					[
						82838.7096774195,
						1,
						96.7741935483937,
						""
					],
					[
						82065.0967741936,
						1,
						0,
						""
					],
					[
						82258.6451612903,
						3,
						0,
						""
					],
					[
						82452.1935483871,
						2,
						0,
						""
					],
					[
						82644.9677419355,
						0,
						0,
						""
					],
					[
						83032.8387096774,
						3,
						290.322580645156,
						""
					],
					[
						83419.935483871,
						0,
						0,
						""
					]
				],
				"bpm": 0,
				"changeBPM": null,
				"mustHitSection": true
			},
			{
				"lengthInSteps": 16,
				"sectionNotes": [
					[
						83612.9677419355,
						3,
						290,
						""
					],
					[
						84000.5806451613,
						0,
						0,
						""
					],
					[
						84194.1290322581,
						0,
						0,
						""
					],
					[
						84386.9677419355,
						2,
						0,
						""
					],
					[
						84581.2258064516,
						1,
						0,
						""
					],
					[
						84774.7741935484,
						2,
						0,
						""
					],
					[
						84968.3225806452,
						0,
						0,
						""
					]
				],
				"bpm": 0,
				"changeBPM": null,
				"mustHitSection": true
			},
			{
				"lengthInSteps": 16,
				"sectionNotes": [
					[
						85161.8709677419,
						1,
						0,
						""
					],
					[
						85355.4193548387,
						0,
						0,
						""
					],
					[
						85548.9677419355,
						2,
						0,
						""
					],
					[
						85742.5161290323,
						3,
						0,
						""
					],
					[
						85936.064516129,
						0,
						0,
						""
					],
					[
						86129.6129032258,
						0,
						0,
						""
					],
					[
						86323.1612903226,
						1,
						0,
						""
					],
					[
						86516.7096774194,
						1,
						193.548387096769,
						""
					]
				],
				"bpm": 0,
				"changeBPM": null,
				"mustHitSection": true
			},
			{
				"lengthInSteps": 16,
				"sectionNotes": [
					[
						86709.6774193549,
						0,
						193.548387096773,
						""
					],
					[
						87096.9677419355,
						3,
						0,
						""
					],
					[
						87290.3225806452,
						1,
						0,
						""
					],
					[
						87484.4516129032,
						0,
						0,
						""
					],
					[
						87678,
						2,
						0,
						""
					],
					[
						87870.9677419355,
						1,
						0,
						""
					],
					[
						88064.9677419355,
						3,
						0,
						""
					]
				],
				"bpm": 0,
				"changeBPM": null,
				"mustHitSection": false
			},
			{
				"lengthInSteps": 16,
				"sectionNotes": [
					[
						89419.3548387098,
						0,
						96.7741935483791,
						""
					],
					[
						88258.6451612903,
						0,
						0,
						""
					],
					[
						88452.1935483871,
						1,
						0,
						""
					],
					[
						88645.7419354839,
						2,
						0,
						""
					],
					[
						88838.7096774193,
						0,
						0,
						""
					],
					[
						89032.8387096774,
						3,
						0,
						""
					],
					[
						89226.3870967742,
						2,
						0,
						""
					],
					[
						89613.4838709678,
						3,
						0,
						""
					]
				],
				"bpm": 0,
				"changeBPM": null,
				"mustHitSection": false
			},
			{
				"lengthInSteps": 16,
				"sectionNotes": [
					[
						89806.9677419355,
						0,
						0,
						""
					],
					[
						90193.9677419355,
						0,
						0,
						""
					],
					[
						90387.0967741935,
						2,
						0,
						""
					],
					[
						90581.2258064516,
						0,
						0,
						""
					],
					[
						90773.9677419355,
						2,
						0,
						""
					],
					[
						90967.7419354839,
						3,
						0,
						""
					],
					[
						91160.9677419355,
						1,
						0,
						""
					]
				],
				"bpm": 0,
				"changeBPM": null,
				"mustHitSection": false
			},
			{
				"lengthInSteps": 16,
				"sectionNotes": [
					[
						91354.9677419355,
						2,
						0,
						""
					],
					[
						91548.9677419355,
						1,
						0,
						""
					],
					[
						91741.9677419355,
						0,
						0,
						""
					],
					[
						91936.064516129,
						3,
						0,
						""
					],
					[
						92128.9677419355,
						0,
						0,
						""
					],
					[
						92322.9677419355,
						1,
						96,
						""
					],
					[
						92515.9677419355,
						2,
						96,
						""
					]
				],
				"bpm": 0,
				"changeBPM": null,
				"mustHitSection": false
			},
			{
				"lengthInSteps": 16,
				"sectionNotes": [
					[
						92903.2258064517,
						0,
						0,
						""
					],
					[
						93096.9677419355,
						0,
						0,
						""
					],
					[
						93289.9677419355,
						3,
						0,
						""
					],
					[
						93483.8709677419,
						1,
						0,
						""
					],
					[
						93678,
						2,
						0,
						""
					],
					[
						93870.9677419355,
						0,
						0,
						""
					],
					[
						94064.9677419355,
						1,
						0,
						""
					],
					[
						94257.9677419355,
						3,
						0,
						""
					]
				],
				"bpm": 0,
				"changeBPM": null,
				"mustHitSection": true
			},
			{
				"lengthInSteps": 16,
				"sectionNotes": [
					[
						94452.1935483871,
						3,
						0,
						""
					],
					[
						94645.7419354839,
						3,
						0,
						""
					],
					[
						94839.2903225807,
						2,
						0,
						""
					],
					[
						95032.2580645161,
						0,
						0,
						""
					],
					[
						95226.3870967742,
						1,
						0,
						""
					],
					[
						95418.9677419355,
						3,
						0,
						""
					],
					[
						95613.4838709678,
						0,
						0,
						""
					],
					[
						95806.9677419355,
						1,
						0,
						""
					]
				],
				"bpm": 0,
				"changeBPM": null,
				"mustHitSection": true
			},
			{
				"lengthInSteps": 16,
				"sectionNotes": [
					[
						96000.0000000001,
						1,
						193.548387096773,
						""
					],
					[
						96386.9677419355,
						0,
						0,
						""
					],
					[
						96580.6451612903,
						3,
						0,
						""
					],
					[
						96774.7741935484,
						2,
						0,
						""
					],
					[
						96968.3225806452,
						1,
						0,
						""
					],
					[
						97161.2903225806,
						0,
						0,
						""
					],
					[
						97355.4193548387,
						3,
						0,
						""
					]
				],
				"bpm": 0,
				"changeBPM": null,
				"mustHitSection": true
			},
			{
				"lengthInSteps": 16,
				"sectionNotes": [
					[
						97548.9677419355,
						2,
						0,
						""
					],
					[
						97742.5161290323,
						3,
						0,
						""
					],
					[
						97935.9677419355,
						0,
						0,
						""
					],
					[
						98129.6129032258,
						3,
						0,
						""
					],
					[
						98322.9677419355,
						1,
						0,
						""
					],
					[
						98516.7096774194,
						3,
						0,
						""
					],
					[
						98709.9677419355,
						2,
						0,
						""
					],
					[
						98903.2258064516,
						2,
						193.548387096774,
						""
					]
				],
				"bpm": 0,
				"changeBPM": null,
				"mustHitSection": true
			},
			{
				"lengthInSteps": 16,
				"sectionNotes": [
					[
						99096.7741935485,
						0,
						290.322580645166,
						""
					],
					[
						99483,
						1,
						0,
						""
					],
					[
						99870.1935483871,
						2,
						0,
						""
					],
					[
						100063,
						3,
						0,
						""
					],
					[
						100258.064516129,
						0,
						0,
						""
					],
					[
						100450,
						1,
						0,
						""
					]
				],
				"bpm": 0,
				"changeBPM": null,
				"mustHitSection": false
			},
			{
				"lengthInSteps": 16,
				"sectionNotes": [
					[
						100645.161290323,
						3,
						0,
						""
					],
					[
						101031,
						3,
						0,
						""
					],
					[
						101418,
						3,
						0,
						""
					],
					[
						101805.677419355,
						1,
						0,
						""
					],
					[
						101999.225806452,
						0,
						0,
						""
					]
				],
				"bpm": 0,
				"changeBPM": null,
				"mustHitSection": false
			},
			{
				"lengthInSteps": 16,
				"sectionNotes": [
					[
						102193.548387097,
						0,
						290.322580645166,
						""
					],
					[
						102579,
						1,
						0,
						""
					],
					[
						102966.967741935,
						2,
						0,
						""
					],
					[
						103160,
						3,
						0,
						""
					],
					[
						103354.838709677,
						0,
						0,
						""
					],
					[
						103547,
						1,
						0,
						""
					]
				],
				"bpm": 0,
				"changeBPM": null,
				"mustHitSection": true
			},
			{
				"lengthInSteps": 16,
				"sectionNotes": [
					[
						103741.935483871,
						3,
						0,
						""
					],
					[
						104128,
						3,
						0,
						""
					],
					[
						104515.35483871,
						1,
						0,
						""
					],
					[
						104708.903225806,
						0,
						0,
						""
					],
					[
						104902.451612903,
						3,
						0,
						""
					]
				],
				"bpm": 0,
				"changeBPM": null,
				"mustHitSection": true
			},
			{
				"lengthInSteps": 16,
				"sectionNotes": [
					[
						105290.322580645,
						2,
						290.322580645166,
						""
					],
					[
						105676,
						1,
						0,
						""
					],
					[
						106063.741935484,
						2,
						0,
						""
					],
					[
						106257,
						3,
						0,
						""
					],
					[
						106451.612903226,
						0,
						0,
						""
					],
					[
						106644,
						1,
						0,
						""
					]
				],
				"bpm": 0,
				"changeBPM": null,
				"mustHitSection": false
			},
			{
				"lengthInSteps": 16,
				"sectionNotes": [
					[
						106838.70967742,
						0,
						0,
						""
					],
					[
						107031,
						1,
						0,
						""
					],
					[
						107225,
						3,
						0,
						""
					],
					[
						107418,
						1,
						0,
						""
					],
					[
						107612.129032258,
						0,
						0,
						""
					],
					[
						107999,
						3,
						0,
						""
					],
					[
						108192,
						3,
						0,
						""
					]
				],
				"bpm": 0,
				"changeBPM": null,
				"mustHitSection": false
			},
			{
				"lengthInSteps": 16,
				"sectionNotes": [
					[
						108387.096774194,
						2,
						290.322580645166,
						""
					],
					[
						108773,
						3,
						0,
						""
					],
					[
						109160.516129032,
						2,
						0,
						""
					],
					[
						109354.064516129,
						3,
						0,
						""
					],
					[
						109547,
						0,
						0,
						""
					],
					[
						109741,
						1,
						0,
						""
					]
				],
				"bpm": 0,
				"changeBPM": null,
				"mustHitSection": true
			},
			{
				"lengthInSteps": 16,
				"sectionNotes": [
					[
						109935.483870968,
						0,
						0,
						""
					],
					[
						110321,
						3,
						0,
						""
					],
					[
						110515,
						1,
						0,
						""
					],
					[
						110708,
						3,
						0,
						""
					],
					[
						110902.451612903,
						2,
						0,
						""
					],
					[
						111096,
						3,
						0,
						""
					],
					[
						111289.548387097,
						0,
						0,
						""
					]
				],
				"bpm": 0,
				"changeBPM": null,
				"mustHitSection": true
			},
			{
				"lengthInSteps": 16,
				"sectionNotes": [
					[
						111483.870967742,
						1,
						0,
						""
					],
					[
						111677.806451613,
						0,
						0,
						""
					],
					[
						111774.580645161,
						2,
						0,
						""
					],
					[
						111870.967741935,
						3,
						0,
						""
					],
					[
						112064.903225806,
						0,
						0,
						""
					],
					[
						112258,
						1,
						0,
						""
					],
					[
						112452,
						0,
						0,
						""
					],
					[
						112548.774193548,
						1,
						0,
						""
					],
					[
						112645.161290323,
						3,
						0,
						""
					],
					[
						112839.096774194,
						0,
						0,
						""
					]
				],
				"bpm": 0,
				"changeBPM": null,
				"mustHitSection": false
			},
			{
				"lengthInSteps": 16,
				"sectionNotes": [
					[
						113032.258064516,
						1,
						0,
						""
					],
					[
						113226.193548387,
						3,
						0,
						""
					],
					[
						113322.967741935,
						0,
						0,
						""
					],
					[
						113419.741935484,
						2,
						0,
						""
					],
					[
						113613.290322581,
						0,
						0,
						""
					],
					[
						113806.838709677,
						3,
						0,
						""
					],
					[
						114000.387096774,
						0,
						0,
						""
					],
					[
						114097.161290323,
						1,
						0,
						""
					],
					[
						114193.548387097,
						2,
						0,
						""
					],
					[
						114387.483870968,
						0,
						0,
						""
					],
					[
						114484.258064516,
						3,
						0,
						""
					]
				],
				"bpm": 0,
				"changeBPM": null,
				"mustHitSection": false
			},
			{
				"lengthInSteps": 16,
				"sectionNotes": [
					[
						114581,
						1,
						0,
						""
					],
					[
						114774.806451613,
						0,
						0,
						""
					],
					[
						114871.580645161,
						2,
						0,
						""
					],
					[
						114967.741935484,
						3,
						0,
						""
					],
					[
						115161.903225806,
						0,
						0,
						""
					],
					[
						115355,
						1,
						0,
						""
					],
					[
						115549,
						0,
						0,
						""
					],
					[
						115645.774193548,
						1,
						0,
						""
					],
					[
						115741.935483871,
						3,
						0,
						""
					],
					[
						115936.096774194,
						0,
						0,
						""
					]
				],
				"bpm": 0,
				"changeBPM": null,
				"mustHitSection": true
			},
			{
				"lengthInSteps": 16,
				"sectionNotes": [
					[
						116129.032258065,
						1,
						0,
						""
					],
					[
						116323.193548387,
						3,
						0,
						""
					],
					[
						116419.967741935,
						0,
						0,
						""
					],
					[
						116516.741935484,
						2,
						0,
						""
					],
					[
						116710.290322581,
						0,
						0,
						""
					],
					[
						116903.838709677,
						3,
						0,
						""
					],
					[
						117097.387096774,
						0,
						0,
						""
					],
					[
						117194.161290323,
						1,
						0,
						""
					],
					[
						117290.322580645,
						2,
						0,
						""
					],
					[
						117484.483870968,
						0,
						0,
						""
					],
					[
						117581.258064516,
						3,
						0,
						""
					]
				],
				"bpm": 0,
				"changeBPM": null,
				"mustHitSection": true
			},
			{
				"lengthInSteps": 16,
				"sectionNotes": [
					[
						117678,
						1,
						0,
						""
					],
					[
						117871.806451613,
						0,
						0,
						""
					],
					[
						117968.580645161,
						2,
						0,
						""
					],
					[
						118064.516129032,
						3,
						0,
						""
					],
					[
						118258.903225806,
						0,
						0,
						""
					],
					[
						118452,
						1,
						0,
						""
					],
					[
						118646,
						0,
						0,
						""
					],
					[
						118742.774193548,
						1,
						0,
						""
					],
					[
						118838.709677419,
						3,
						0,
						""
					],
					[
						119033.096774194,
						0,
						0,
						""
					]
				],
				"bpm": 0,
				"changeBPM": null,
				"mustHitSection": false
			},
			{
				"lengthInSteps": 16,
				"sectionNotes": [
					[
						119226,
						1,
						0,
						""
					],
					[
						119420.193548387,
						3,
						0,
						""
					],
					[
						119516.967741935,
						0,
						0,
						""
					],
					[
						119613.741935484,
						2,
						0,
						""
					],
					[
						119807.290322581,
						0,
						0,
						""
					],
					[
						120000.838709677,
						3,
						0,
						""
					],
					[
						120194.387096774,
						0,
						0,
						""
					],
					[
						120291.161290323,
						1,
						0,
						""
					],
					[
						120387.096774194,
						2,
						0,
						""
					],
					[
						120581.483870968,
						0,
						0,
						""
					],
					[
						120678.258064516,
						3,
						0,
						""
					]
				],
				"bpm": 0,
				"changeBPM": null,
				"mustHitSection": false
			},
			{
				"lengthInSteps": 16,
				"sectionNotes": [
					[
						120774.193548387,
						1,
						0,
						""
					],
					[
						120967.806451613,
						0,
						0,
						""
					],
					[
						121064.580645161,
						2,
						0,
						""
					],
					[
						121161.290322581,
						3,
						0,
						""
					],
					[
						121354.903225806,
						0,
						0,
						""
					],
					[
						121548,
						1,
						0,
						""
					],
					[
						121742,
						0,
						0,
						""
					],
					[
						121838.774193548,
						1,
						0,
						""
					],
					[
						121935.483870968,
						3,
						0,
						""
					],
					[
						122129.096774194,
						0,
						0,
						""
					]
				],
				"bpm": 0,
				"changeBPM": null,
				"mustHitSection": true
			},
			{
				"lengthInSteps": 16,
				"sectionNotes": [
					[
						122322.580645161,
						1,
						0,
						""
					],
					[
						122516.193548387,
						3,
						0,
						""
					],
					[
						122612.967741935,
						0,
						0,
						""
					],
					[
						122709.741935484,
						2,
						0,
						""
					],
					[
						122903.290322581,
						0,
						0,
						""
					],
					[
						123096.838709677,
						3,
						0,
						""
					],
					[
						123290.387096774,
						0,
						0,
						""
					],
					[
						123387.161290323,
						1,
						0,
						""
					],
					[
						123483.870967742,
						2,
						0,
						""
					],
					[
						123677.483870968,
						0,
						0,
						""
					],
					[
						123774.258064516,
						3,
						0,
						""
					]
				],
				"bpm": 0,
				"changeBPM": null,
				"mustHitSection": true
			},
			{
				"lengthInSteps": 16,
				"sectionNotes": [],
				"bpm": 0,
				"changeBPM": false,
				"mustHitSection": true
			},
			{
				"lengthInSteps": 16,
				"sectionNotes": [],
				"bpm": 155,
				"changeBPM": false,
				"mustHitSection": true
			}
		],
		"gf": "Nene",
		"bpm": 155,
		"song": "Darnell"
	}
}